{
"meta":{"test_sets":[],"test_metrics":[],"learn_metrics":[{"best_value":"Min","name":"RMSE"}],"launch_mode":"Train","parameters":"","iteration_count":1000,"learn_sets":["learn"],"name":"experiment"},
"iterations":[
{"learn":[14.91086291],"iteration":0,"passed_time":0.05529564861,"remaining_time":55.24035297},
{"learn":[14.55020557],"iteration":1,"passed_time":0.05566227902,"remaining_time":27.77547723},
{"learn":[14.17681715],"iteration":2,"passed_time":0.05607232673,"remaining_time":18.63470325},
{"learn":[13.81057212],"iteration":3,"passed_time":0.05651533326,"remaining_time":14.07231798},
{"learn":[13.46757144],"iteration":4,"passed_time":0.05714913428,"remaining_time":11.37267772},
{"learn":[13.13718757],"iteration":5,"passed_time":0.05761830786,"remaining_time":9.545433002},
{"learn":[12.83600231],"iteration":6,"passed_time":0.05798722997,"remaining_time":8.225902765},
{"learn":[12.55008331],"iteration":7,"passed_time":0.05827685924,"remaining_time":7.226330545},
{"learn":[12.2906159],"iteration":8,"passed_time":0.05861803093,"remaining_time":6.454496517},
{"learn":[11.99817751],"iteration":9,"passed_time":0.0589142853,"remaining_time":5.832514245},
{"learn":[11.70478879],"iteration":10,"passed_time":0.05920012285,"remaining_time":5.322629227},
{"learn":[11.43914558],"iteration":11,"passed_time":0.05960767052,"remaining_time":4.907698207},
{"learn":[11.21252779],"iteration":12,"passed_time":0.05997642596,"remaining_time":4.553594802},
{"learn":[10.95367854],"iteration":13,"passed_time":0.06035655657,"remaining_time":4.250826055},
{"learn":[10.71430381],"iteration":14,"passed_time":0.06070581172,"remaining_time":3.986348303},
{"learn":[10.4790983],"iteration":15,"passed_time":0.06104131666,"remaining_time":3.754040975},
{"learn":[10.25368452],"iteration":16,"passed_time":0.06136402975,"remaining_time":3.548284779},
{"learn":[10.05101673],"iteration":17,"passed_time":0.06175003545,"remaining_time":3.368807489},
{"learn":[9.831146722],"iteration":18,"passed_time":0.06206033169,"remaining_time":3.204272915},
{"learn":[9.636702627],"iteration":19,"passed_time":0.06236250281,"remaining_time":3.055762638},
{"learn":[9.45890275],"iteration":20,"passed_time":0.06270842458,"remaining_time":2.923407031},
{"learn":[9.305040813],"iteration":21,"passed_time":0.06316288961,"remaining_time":2.807877547},
{"learn":[9.127155693],"iteration":22,"passed_time":0.06351572815,"remaining_time":2.698037669},
{"learn":[8.96078391],"iteration":23,"passed_time":0.0645389099,"remaining_time":2.624582336},
{"learn":[8.801525487],"iteration":24,"passed_time":0.06486095631,"remaining_time":2.529577296},
{"learn":[8.659288795],"iteration":25,"passed_time":0.06518750279,"remaining_time":2.442024143},
{"learn":[8.505777776],"iteration":26,"passed_time":0.0655044658,"remaining_time":2.36058686},
{"learn":[8.371623936],"iteration":27,"passed_time":0.06586551279,"remaining_time":2.28647423},
{"learn":[8.221221692],"iteration":28,"passed_time":0.06627297713,"remaining_time":2.219002096},
{"learn":[8.086950708],"iteration":29,"passed_time":0.06663510747,"remaining_time":2.154535142},
{"learn":[7.975173598],"iteration":30,"passed_time":0.06703390502,"remaining_time":2.095350128},
{"learn":[7.841325817],"iteration":31,"passed_time":0.06736895162,"remaining_time":2.037910787},
{"learn":[7.724731574],"iteration":32,"passed_time":0.06770095652,"remaining_time":1.98384318},
{"learn":[7.627704629],"iteration":33,"passed_time":0.06801079442,"remaining_time":1.932306689},
{"learn":[7.509750623],"iteration":34,"passed_time":0.06841342536,"remaining_time":1.886255871},
{"learn":[7.413201288],"iteration":35,"passed_time":0.0687873892,"remaining_time":1.841973422},
{"learn":[7.31471594],"iteration":36,"passed_time":0.06922235395,"remaining_time":1.801652077},
{"learn":[7.233183686],"iteration":37,"passed_time":0.06973290314,"remaining_time":1.765343495},
{"learn":[7.142946074],"iteration":38,"passed_time":0.07027553615,"remaining_time":1.731661288},
{"learn":[7.06262018],"iteration":39,"passed_time":0.07065250004,"remaining_time":1.695660001},
{"learn":[6.984715359],"iteration":40,"passed_time":0.07099500509,"remaining_time":1.660590485},
{"learn":[6.916560934],"iteration":41,"passed_time":0.07197756124,"remaining_time":1.641773897},
{"learn":[6.833291011],"iteration":42,"passed_time":0.07232431635,"remaining_time":1.609636529},
{"learn":[6.770865576],"iteration":43,"passed_time":0.07267652988,"remaining_time":1.579062786},
{"learn":[6.699646148],"iteration":44,"passed_time":0.07294770054,"remaining_time":1.548112312},
{"learn":[6.638160575],"iteration":45,"passed_time":0.07333208121,"remaining_time":1.520843597},
{"learn":[6.564463242],"iteration":46,"passed_time":0.07369850328,"remaining_time":1.494354758},
{"learn":[6.502987327],"iteration":47,"passed_time":0.07408159226,"remaining_time":1.469284913},
{"learn":[6.439645175],"iteration":48,"passed_time":0.07440559704,"remaining_time":1.444075975},
{"learn":[6.374093549],"iteration":49,"passed_time":0.07478422762,"remaining_time":1.420900325},
{"learn":[6.324067038],"iteration":50,"passed_time":0.07509185716,"remaining_time":1.397297499},
{"learn":[6.269864592],"iteration":51,"passed_time":0.07540307008,"remaining_time":1.37465597},
{"learn":[6.220692922],"iteration":52,"passed_time":0.07575211689,"remaining_time":1.353533107},
{"learn":[6.170153496],"iteration":53,"passed_time":0.07610374708,"remaining_time":1.333224902},
{"learn":[6.126150692],"iteration":54,"passed_time":0.07645196054,"remaining_time":1.313583686},
{"learn":[6.081952678],"iteration":55,"passed_time":0.07672971464,"remaining_time":1.293443761},
{"learn":[6.038436299],"iteration":56,"passed_time":0.07704880268,"remaining_time":1.274684578},
{"learn":[6.003818077],"iteration":57,"passed_time":0.07736884906,"remaining_time":1.256576824},
{"learn":[5.959911571],"iteration":58,"passed_time":0.07774722964,"remaining_time":1.240002425},
{"learn":[5.928286453],"iteration":59,"passed_time":0.07801806697,"remaining_time":1.222283049},
{"learn":[5.894282286],"iteration":60,"passed_time":0.07834144674,"remaining_time":1.205944565},
{"learn":[5.858817089],"iteration":61,"passed_time":0.07869203524,"remaining_time":1.19053434},
{"learn":[5.821997977],"iteration":62,"passed_time":0.07901316497,"remaining_time":1.175164057},
{"learn":[5.786378845],"iteration":63,"passed_time":0.07931658611,"remaining_time":1.160005072},
{"learn":[5.753071179],"iteration":64,"passed_time":0.07959921528,"remaining_time":1.145004097},
{"learn":[5.719565692],"iteration":65,"passed_time":0.07989980305,"remaining_time":1.130703273},
{"learn":[5.688473593],"iteration":66,"passed_time":0.08016243192,"remaining_time":1.116291776},
{"learn":[5.657878883],"iteration":67,"passed_time":0.08045351954,"remaining_time":1.102686474},
{"learn":[5.631193074],"iteration":68,"passed_time":0.08075410731,"remaining_time":1.089595274},
{"learn":[5.604419233],"iteration":69,"passed_time":0.08103319476,"remaining_time":1.076583873},
{"learn":[5.579241386],"iteration":70,"passed_time":0.081321074,"remaining_time":1.064046165},
{"learn":[5.558359693],"iteration":71,"passed_time":0.08157816113,"remaining_time":1.051451855},
{"learn":[5.539631523],"iteration":72,"passed_time":0.08183937331,"remaining_time":1.039247932},
{"learn":[5.515214036],"iteration":73,"passed_time":0.0821209608,"remaining_time":1.027621753},
{"learn":[5.494781441],"iteration":74,"passed_time":0.08238638138,"remaining_time":1.016098704},
{"learn":[5.472515418],"iteration":75,"passed_time":0.08268913584,"remaining_time":1.005325809},
{"learn":[5.456295439],"iteration":76,"passed_time":0.08297018165,"remaining_time":0.994564645},
{"learn":[5.431146514],"iteration":77,"passed_time":0.08325564419,"remaining_time":0.9841244095},
{"learn":[5.414894443],"iteration":78,"passed_time":0.08353148159,"remaining_time":0.9738290449},
{"learn":[5.396495646],"iteration":79,"passed_time":0.08387702835,"remaining_time":0.9645858261},
{"learn":[5.377702525],"iteration":80,"passed_time":0.08414511564,"remaining_time":0.9546834725},
{"learn":[5.360561158],"iteration":81,"passed_time":0.08442878649,"remaining_time":0.9451905609},
{"learn":[5.341155573],"iteration":82,"passed_time":0.08479895861,"remaining_time":0.9368752415},
{"learn":[5.326623653],"iteration":83,"passed_time":0.08512608844,"remaining_time":0.9282797263},
{"learn":[5.309576272],"iteration":84,"passed_time":0.08545951002,"remaining_time":0.9199464902},
{"learn":[5.295845342],"iteration":85,"passed_time":0.08580409843,"remaining_time":0.9119179764},
{"learn":[5.280988092],"iteration":86,"passed_time":0.08606897734,"remaining_time":0.9032296128},
{"learn":[5.269075664],"iteration":87,"passed_time":0.0870680754,"remaining_time":0.9023418723},
{"learn":[5.255808012],"iteration":88,"passed_time":0.08736262141,"remaining_time":0.8942398664},
{"learn":[5.239504307],"iteration":89,"passed_time":0.08763904215,"remaining_time":0.8861280929},
{"learn":[5.226990368],"iteration":90,"passed_time":0.08791321286,"remaining_time":0.8781660494},
{"learn":[5.216047389],"iteration":91,"passed_time":0.08821575899,"remaining_time":0.8706511866},
{"learn":[5.198797632],"iteration":92,"passed_time":0.08853426369,"remaining_time":0.8634470663},
{"learn":[5.186157892],"iteration":93,"passed_time":0.08880622603,"remaining_time":0.8559408594},
{"learn":[5.174155311],"iteration":94,"passed_time":0.08905939643,"remaining_time":0.8484079344},
{"learn":[5.161461959],"iteration":95,"passed_time":0.0893403589,"remaining_time":0.8412883797},
{"learn":[5.148454658],"iteration":96,"passed_time":0.08960152942,"remaining_time":0.834125578},
{"learn":[5.138403398],"iteration":97,"passed_time":0.08987836684,"remaining_time":0.8272478254},
{"learn":[5.123177996],"iteration":98,"passed_time":0.09016287103,"remaining_time":0.8205732},
{"learn":[5.113301061],"iteration":99,"passed_time":0.09048983419,"remaining_time":0.8144085077},
{"learn":[5.10275177],"iteration":100,"passed_time":0.09076937997,"remaining_time":0.8079373524},
{"learn":[5.092853053],"iteration":101,"passed_time":0.09103963396,"remaining_time":0.801505797},
{"learn":[5.084913283],"iteration":102,"passed_time":0.0913179714,"remaining_time":0.7952642752},
{"learn":[5.072121969],"iteration":103,"passed_time":0.09163789278,"remaining_time":0.7894956916},
{"learn":[5.062354922],"iteration":104,"passed_time":0.09195093906,"remaining_time":0.7837722901},
{"learn":[5.055791314],"iteration":105,"passed_time":0.09237944538,"remaining_time":0.7791247563},
{"learn":[5.047253247],"iteration":106,"passed_time":0.09278432635,"remaining_time":0.7743589106},
{"learn":[5.039527137],"iteration":107,"passed_time":0.09309883099,"remaining_time":0.7689273819},
{"learn":[5.032455486],"iteration":108,"passed_time":0.09346362803,"remaining_time":0.7640008493},
{"learn":[5.023271581],"iteration":109,"passed_time":0.09380034133,"remaining_time":0.7589300344},
{"learn":[5.014636627],"iteration":110,"passed_time":0.09409347065,"remaining_time":0.7535954541},
{"learn":[5.00831561],"iteration":111,"passed_time":0.0943815999,"remaining_time":0.7483112563},
{"learn":[4.999928354],"iteration":112,"passed_time":0.09466347906,"remaining_time":0.7430664241},
{"learn":[4.989833092],"iteration":113,"passed_time":0.09510169385,"remaining_time":0.7391236908},
{"learn":[4.981666294],"iteration":114,"passed_time":0.09538136464,"remaining_time":0.7340218061},
{"learn":[4.973543792],"iteration":115,"passed_time":0.09567574398,"remaining_time":0.7291151524},
{"learn":[4.96534363],"iteration":116,"passed_time":0.09600099878,"remaining_time":0.7245203583},
{"learn":[4.959793895],"iteration":117,"passed_time":0.09631642009,"remaining_time":0.7199244282},
{"learn":[4.95158519],"iteration":118,"passed_time":0.09665046669,"remaining_time":0.715538329},
{"learn":[4.946335234],"iteration":119,"passed_time":0.09696034625,"remaining_time":0.7110425392},
{"learn":[4.93679246],"iteration":120,"passed_time":0.09726022568,"remaining_time":0.7065432923},
{"learn":[4.933372301],"iteration":121,"passed_time":0.09758873052,"remaining_time":0.7023188967},
{"learn":[4.929399284],"iteration":122,"passed_time":0.09814194701,"remaining_time":0.6997600612},
{"learn":[4.924071666],"iteration":123,"passed_time":0.09846586845,"remaining_time":0.6956137158},
{"learn":[4.920891637],"iteration":124,"passed_time":0.09861695401,"remaining_time":0.6903186781},
{"learn":[4.913043218],"iteration":125,"passed_time":0.09888462463,"remaining_time":0.6859139835},
{"learn":[4.907040054],"iteration":126,"passed_time":0.0991677538,"remaining_time":0.6816807013},
{"learn":[4.898107968],"iteration":127,"passed_time":0.09943259104,"remaining_time":0.6773845264},
{"learn":[4.894518077],"iteration":128,"passed_time":0.09963946909,"remaining_time":0.6727595161},
{"learn":[4.888113722],"iteration":129,"passed_time":0.09996414054,"remaining_time":0.6689907867},
{"learn":[4.882848375],"iteration":130,"passed_time":0.1002336028,"remaining_time":0.6649084036},
{"learn":[4.879607808],"iteration":131,"passed_time":0.1005203571,"remaining_time":0.6609974996},
{"learn":[4.87187003],"iteration":132,"passed_time":0.1008623205,"remaining_time":0.6575009912},
{"learn":[4.868208415],"iteration":133,"passed_time":0.1011644499,"remaining_time":0.6537941315},
{"learn":[4.860157997],"iteration":134,"passed_time":0.1014418707,"remaining_time":0.6499793935},
{"learn":[4.853808725],"iteration":135,"passed_time":0.1017318749,"remaining_time":0.6462966173},
{"learn":[4.848509747],"iteration":136,"passed_time":0.1019882954,"remaining_time":0.6424518169},
{"learn":[4.841835156],"iteration":137,"passed_time":0.1022657995,"remaining_time":0.6387907185},
{"learn":[4.837115543],"iteration":138,"passed_time":0.102551887,"remaining_time":0.6352314729},
{"learn":[4.832963901],"iteration":139,"passed_time":0.1028489747,"remaining_time":0.6317865591},
{"learn":[4.827497571],"iteration":140,"passed_time":0.1032556474,"remaining_time":0.6290539087},
{"learn":[4.822536751],"iteration":141,"passed_time":0.1038289059,"remaining_time":0.627360572},
{"learn":[4.821521513],"iteration":142,"passed_time":0.103952741,"remaining_time":0.6229895039},
{"learn":[4.817340959],"iteration":143,"passed_time":0.1042750374,"remaining_time":0.619857167},
{"learn":[4.811946899],"iteration":144,"passed_time":0.104694877,"remaining_time":0.6173387572},
{"learn":[4.804501056],"iteration":145,"passed_time":0.1057417674,"remaining_time":0.6185169134},
{"learn":[4.797719087],"iteration":146,"passed_time":0.1065084037,"remaining_time":0.6180385602},
{"learn":[4.79439495],"iteration":147,"passed_time":0.1070895373,"remaining_time":0.6164884172},
{"learn":[4.791917978],"iteration":148,"passed_time":0.1074086253,"remaining_time":0.6134546318},
{"learn":[4.786095817],"iteration":149,"passed_time":0.1079140494,"remaining_time":0.6115129467},
{"learn":[4.784376258],"iteration":150,"passed_time":0.1081970536,"remaining_time":0.6083397252},
{"learn":[4.781120057],"iteration":151,"passed_time":0.1086798107,"remaining_time":0.606318944},
{"learn":[4.774601405],"iteration":152,"passed_time":0.1090818166,"remaining_time":0.6038712333},
{"learn":[4.76794172],"iteration":153,"passed_time":0.1103745024,"remaining_time":0.6063430455},
{"learn":[4.764014928],"iteration":154,"passed_time":0.1108526344,"remaining_time":0.6043256521},
{"learn":[4.759147995],"iteration":155,"passed_time":0.1111975562,"remaining_time":0.6016072911},
{"learn":[4.753334372],"iteration":156,"passed_time":0.1115427279,"remaining_time":0.5989205073},
{"learn":[4.747029324],"iteration":157,"passed_time":0.1118856913,"remaining_time":0.5962515955},
{"learn":[4.743924435],"iteration":158,"passed_time":0.1123400313,"remaining_time":0.5942010463},
{"learn":[4.738998434],"iteration":159,"passed_time":0.1127799962,"remaining_time":0.5920949799},
{"learn":[4.737259414],"iteration":160,"passed_time":0.1129791241,"remaining_time":0.588754566},
{"learn":[4.733727827],"iteration":161,"passed_time":0.113287712,"remaining_time":0.5860191521},
{"learn":[4.72623706],"iteration":162,"passed_time":0.1136192169,"remaining_time":0.5834311934},
{"learn":[4.722644791],"iteration":163,"passed_time":0.1139266381,"remaining_time":0.5807479843},
{"learn":[4.719451822],"iteration":164,"passed_time":0.11428181,"remaining_time":0.5783352202},
{"learn":[4.715121835],"iteration":165,"passed_time":0.1146244817,"remaining_time":0.5758844442},
{"learn":[4.710825485],"iteration":166,"passed_time":0.1149696951,"remaining_time":0.573471593},
{"learn":[4.704297312],"iteration":167,"passed_time":0.1152966583,"remaining_time":0.5709929743},
{"learn":[4.696269361],"iteration":168,"passed_time":0.1157220812,"remaining_time":0.5690239615},
{"learn":[4.691948031],"iteration":169,"passed_time":0.1161199621,"remaining_time":0.5669386384},
{"learn":[4.688101602],"iteration":170,"passed_time":0.1165773855,"remaining_time":0.5651617109},
{"learn":[4.686713079],"iteration":171,"passed_time":0.1170481008,"remaining_time":0.563464113},
{"learn":[4.683505161],"iteration":172,"passed_time":0.1372231482,"remaining_time":0.6559742404},
{"learn":[4.680125139],"iteration":173,"passed_time":0.1381312033,"remaining_time":0.6557262868},
{"learn":[4.676922599],"iteration":174,"passed_time":0.1384655415,"remaining_time":0.6527661244},
{"learn":[4.672615203],"iteration":175,"passed_time":0.1388780893,"remaining_time":0.6502019635},
{"learn":[4.67055474],"iteration":176,"passed_time":0.1395190571,"remaining_time":0.6487242032},
{"learn":[4.667231989],"iteration":177,"passed_time":0.1402638597,"remaining_time":0.6477353522},
{"learn":[4.663459136],"iteration":178,"passed_time":0.1411687897,"remaining_time":0.6474836669},
{"learn":[4.659522634],"iteration":179,"passed_time":0.1420707614,"remaining_time":0.6472112462},
{"learn":[4.655005447],"iteration":180,"passed_time":0.1437591613,"remaining_time":0.6504903485},
{"learn":[4.648337252],"iteration":181,"passed_time":0.1455556877,"remaining_time":0.6542008383},
{"learn":[4.643395739],"iteration":182,"passed_time":0.1459271099,"remaining_time":0.6514887911},
{"learn":[4.640483884],"iteration":183,"passed_time":0.1487646517,"remaining_time":0.6597388903},
{"learn":[4.636935885],"iteration":184,"passed_time":0.1492171167,"remaining_time":0.6573618926},
{"learn":[4.633816428],"iteration":185,"passed_time":0.149552455,"remaining_time":0.654493002},
{"learn":[4.63152792],"iteration":186,"passed_time":0.1498295424,"remaining_time":0.6513979572},
{"learn":[4.629685084],"iteration":187,"passed_time":0.1501075049,"remaining_time":0.6483366699},
{"learn":[4.626785841],"iteration":188,"passed_time":0.1504193011,"remaining_time":0.645450017},
{"learn":[4.620812926],"iteration":189,"passed_time":0.1508062235,"remaining_time":0.6429107423},
{"learn":[4.613184256],"iteration":190,"passed_time":0.151181604,"remaining_time":0.6403451186},
{"learn":[4.610413231],"iteration":191,"passed_time":0.1514852335,"remaining_time":0.6375003577},
{"learn":[4.604509952],"iteration":192,"passed_time":0.1517751961,"remaining_time":0.6346247837},
{"learn":[4.599963693],"iteration":193,"passed_time":0.1520721172,"remaining_time":0.6318047754},
{"learn":[4.593356982],"iteration":194,"passed_time":0.1523831634,"remaining_time":0.6290689566},
{"learn":[4.589644522],"iteration":195,"passed_time":0.1526608758,"remaining_time":0.6262211437},
{"learn":[4.585410624],"iteration":196,"passed_time":0.153325594,"remaining_time":0.6249769135},
{"learn":[4.582990301],"iteration":197,"passed_time":0.1538608935,"remaining_time":0.6232143263},
{"learn":[4.575760649],"iteration":198,"passed_time":0.1545605705,"remaining_time":0.6221257135},
{"learn":[4.566716793],"iteration":199,"passed_time":0.1551404957,"remaining_time":0.6205619829},
{"learn":[4.560119451],"iteration":200,"passed_time":0.1554790424,"remaining_time":0.6180485317},
{"learn":[4.556779633],"iteration":201,"passed_time":0.155907007,"remaining_time":0.6159098595},
{"learn":[4.55293038],"iteration":202,"passed_time":0.156219845,"remaining_time":0.6133360416},
{"learn":[4.550553331],"iteration":203,"passed_time":0.1565111826,"remaining_time":0.6107004968},
{"learn":[4.546677316],"iteration":204,"passed_time":0.1568440208,"remaining_time":0.6082487638},
{"learn":[4.542774037],"iteration":205,"passed_time":0.1571938177,"remaining_time":0.6058829671},
{"learn":[4.540763337],"iteration":206,"passed_time":0.1575269893,"remaining_time":0.6034729588},
{"learn":[4.536869047],"iteration":207,"passed_time":0.157869161,"remaining_time":0.6011171898},
{"learn":[4.532497688],"iteration":208,"passed_time":0.1581826656,"remaining_time":0.5986721937},
{"learn":[4.530345198],"iteration":209,"passed_time":0.1584599197,"remaining_time":0.5961111264},
{"learn":[4.52426877],"iteration":210,"passed_time":0.1587194235,"remaining_time":0.5935053324},
{"learn":[4.520559681],"iteration":211,"passed_time":0.1589954276,"remaining_time":0.5909830044},
{"learn":[4.518918908],"iteration":212,"passed_time":0.159317474,"remaining_time":0.5886518874},
{"learn":[4.516368248],"iteration":213,"passed_time":0.1595838112,"remaining_time":0.5861349329},
{"learn":[4.512747323],"iteration":214,"passed_time":0.1598743155,"remaining_time":0.583727152},
{"learn":[4.510703134],"iteration":215,"passed_time":0.1601701116,"remaining_time":0.5813581827},
{"learn":[4.505535975],"iteration":216,"passed_time":0.160468741,"remaining_time":0.5790185446},
{"learn":[4.502889389],"iteration":217,"passed_time":0.160852955,"remaining_time":0.5770046366},
{"learn":[4.499900145],"iteration":218,"passed_time":0.1612237938,"remaining_time":0.5749579129},
{"learn":[4.496474083],"iteration":219,"passed_time":0.1616152579,"remaining_time":0.5729995506},
{"learn":[4.490927122],"iteration":220,"passed_time":0.1619690964,"remaining_time":0.5709227426},
{"learn":[4.490289599],"iteration":221,"passed_time":0.162256809,"remaining_time":0.568629718},
{"learn":[4.483645373],"iteration":222,"passed_time":0.1625903972,"remaining_time":0.5665145231},
{"learn":[4.479847129],"iteration":223,"passed_time":0.1629869864,"remaining_time":0.5646334887},
{"learn":[4.475625585],"iteration":224,"passed_time":0.1632584488,"remaining_time":0.5623346568},
{"learn":[4.47196016],"iteration":225,"passed_time":0.16356587,"remaining_time":0.5601769175},
{"learn":[4.466700637],"iteration":226,"passed_time":0.1638765412,"remaining_time":0.5580465478},
{"learn":[4.465080889],"iteration":227,"passed_time":0.1642315464,"remaining_time":0.5560822537},
{"learn":[4.460969713],"iteration":228,"passed_time":0.1644964253,"remaining_time":0.5538285762},
{"learn":[4.459378441],"iteration":229,"passed_time":0.164786513,"remaining_time":0.5516765868},
{"learn":[4.457846976],"iteration":230,"passed_time":0.1650496835,"remaining_time":0.5494511109},
{"learn":[4.45705165],"iteration":231,"passed_time":0.16548919,"remaining_time":0.5478262841},
{"learn":[4.452430344],"iteration":232,"passed_time":0.1657791109,"remaining_time":0.5457192192},
{"learn":[4.449748843],"iteration":233,"passed_time":0.1660751986,"remaining_time":0.5436478724},
{"learn":[4.448682759],"iteration":234,"passed_time":0.1663625362,"remaining_time":0.5415631497},
{"learn":[4.445638731],"iteration":235,"passed_time":0.1667229582,"remaining_time":0.5397302544},
{"learn":[4.439964246],"iteration":236,"passed_time":0.1670434212,"remaining_time":0.5377811409},
{"learn":[4.438528313],"iteration":237,"passed_time":0.1675833875,"remaining_time":0.5365484928},
{"learn":[4.437211974],"iteration":238,"passed_time":0.1679539347,"remaining_time":0.5347821936},
{"learn":[4.432430465],"iteration":239,"passed_time":0.1684388585,"remaining_time":0.5333897185},
{"learn":[4.431221768],"iteration":240,"passed_time":0.1687558215,"remaining_time":0.5314758029},
{"learn":[4.426589743],"iteration":241,"passed_time":0.1690571176,"remaining_time":0.5295260129},
{"learn":[4.420191149],"iteration":242,"passed_time":0.1693451635,"remaining_time":0.5275485135},
{"learn":[4.412664332],"iteration":243,"passed_time":0.1696492513,"remaining_time":0.5256345656},
{"learn":[4.408936741],"iteration":244,"passed_time":0.1701680923,"remaining_time":0.5243955497},
{"learn":[4.407416359],"iteration":245,"passed_time":0.1705628065,"remaining_time":0.5227819352},
{"learn":[4.401438941],"iteration":246,"passed_time":0.1710448969,"remaining_time":0.5214445642},
{"learn":[4.39677341],"iteration":247,"passed_time":0.1714604864,"remaining_time":0.5199124425},
{"learn":[4.394566704],"iteration":248,"passed_time":0.1717675742,"remaining_time":0.5180620411},
{"learn":[4.389415423],"iteration":249,"passed_time":0.1720875789,"remaining_time":0.5162627368},
{"learn":[4.388923923],"iteration":250,"passed_time":0.1725365856,"remaining_time":0.5148601696},
{"learn":[4.387887307],"iteration":251,"passed_time":0.1728223398,"remaining_time":0.5129805958},
{"learn":[4.386046921],"iteration":252,"passed_time":0.1731374277,"remaining_time":0.5112002313},
{"learn":[4.384931784],"iteration":253,"passed_time":0.1734792245,"remaining_time":0.5095098482},
{"learn":[4.379699477],"iteration":254,"passed_time":0.1739980654,"remaining_time":0.5083472892},
{"learn":[4.378281762],"iteration":255,"passed_time":0.1743619041,"remaining_time":0.5067392839},
{"learn":[4.374316924],"iteration":256,"passed_time":0.1747028675,"remaining_time":0.505074827},
{"learn":[4.370967],"iteration":257,"passed_time":0.1750679979,"remaining_time":0.5034901334},
{"learn":[4.367714771],"iteration":258,"passed_time":0.1761595973,"remaining_time":0.503993288},
{"learn":[4.36657629],"iteration":259,"passed_time":0.1764840604,"remaining_time":0.5023007874},
{"learn":[4.360936424],"iteration":260,"passed_time":0.1768217321,"remaining_time":0.5006561686},
{"learn":[4.359266792],"iteration":261,"passed_time":0.1771434451,"remaining_time":0.4989765745},
{"learn":[4.35846444],"iteration":262,"passed_time":0.1774863252,"remaining_time":0.4973666223},
{"learn":[4.356210619],"iteration":263,"passed_time":0.1777732878,"remaining_time":0.495610378},
{"learn":[4.352513114],"iteration":264,"passed_time":0.1780685838,"remaining_time":0.4938883362},
{"learn":[4.345521971],"iteration":265,"passed_time":0.1783410878,"remaining_time":0.4921141295},
{"learn":[4.343057215],"iteration":266,"passed_time":0.1786979681,"remaining_time":0.4905828112},
{"learn":[4.340105202],"iteration":267,"passed_time":0.1791135159,"remaining_time":0.4892204985},
{"learn":[4.33978854],"iteration":268,"passed_time":0.1794787712,"remaining_time":0.4877285568},
{"learn":[4.336213925],"iteration":269,"passed_time":0.179778984,"remaining_time":0.4860691049},
{"learn":[4.333933245],"iteration":270,"passed_time":0.1800381962,"remaining_time":0.4843093911},
{"learn":[4.327893545],"iteration":271,"passed_time":0.1803394923,"remaining_time":0.4826733469},
{"learn":[4.323492481],"iteration":272,"passed_time":0.1806987476,"remaining_time":0.4812014267},
{"learn":[4.322145074],"iteration":273,"passed_time":0.1810259607,"remaining_time":0.479652728},
{"learn":[4.319107441],"iteration":274,"passed_time":0.1815069261,"remaining_time":0.4785182598},
{"learn":[4.317946315],"iteration":275,"passed_time":0.1843509264,"remaining_time":0.4835872128},
{"learn":[4.312156445],"iteration":276,"passed_time":0.1848839343,"remaining_time":0.482567092},
{"learn":[4.308102268],"iteration":277,"passed_time":0.1853054822,"remaining_time":0.4812610004},
{"learn":[4.303722605],"iteration":278,"passed_time":0.1858416151,"remaining_time":0.4802573636},
{"learn":[4.298459543],"iteration":279,"passed_time":0.1861297443,"remaining_time":0.4786193425},
{"learn":[4.292533347],"iteration":280,"passed_time":0.1864297071,"remaining_time":0.4770212077},
{"learn":[4.290036069],"iteration":281,"passed_time":0.1868256712,"remaining_time":0.475676709},
{"learn":[4.285476951],"iteration":282,"passed_time":0.1872600526,"remaining_time":0.4744362464},
{"learn":[4.279904997],"iteration":283,"passed_time":0.1875982243,"remaining_time":0.4729589035},
{"learn":[4.276253916],"iteration":284,"passed_time":0.1884189447,"remaining_time":0.4727001596},
{"learn":[4.269035532],"iteration":285,"passed_time":0.188843826,"remaining_time":0.4714492719},
{"learn":[4.263912543],"iteration":286,"passed_time":0.1894669602,"remaining_time":0.4706966641},
{"learn":[4.25833043],"iteration":287,"passed_time":0.1899888845,"remaining_time":0.4696947423},
{"learn":[4.257379221],"iteration":288,"passed_time":0.1904562248,"remaining_time":0.468561854},
{"learn":[4.251749061],"iteration":289,"passed_time":0.1908967729,"remaining_time":0.4673679613},
{"learn":[4.251181474],"iteration":290,"passed_time":0.1917027848,"remaining_time":0.4670696716},
{"learn":[4.248163677],"iteration":291,"passed_time":0.1925343804,"remaining_time":0.466829936},
{"learn":[4.246783559],"iteration":292,"passed_time":0.1939251926,"remaining_time":0.4679355329},
{"learn":[4.243967606],"iteration":293,"passed_time":0.1943791159,"remaining_time":0.4667743396},
{"learn":[4.24079287],"iteration":294,"passed_time":0.1948147057,"remaining_time":0.4655741272},
{"learn":[4.236206311],"iteration":295,"passed_time":0.1954687153,"remaining_time":0.4648985662},
{"learn":[4.234533416],"iteration":296,"passed_time":0.1981942139,"remaining_time":0.4691263715},
{"learn":[4.234136695],"iteration":297,"passed_time":0.1985593859,"remaining_time":0.4677472782},
{"learn":[4.232663089],"iteration":298,"passed_time":0.1989273497,"remaining_time":0.4663815121},
{"learn":[4.23225829],"iteration":299,"passed_time":0.1993229805,"remaining_time":0.4650869545},
{"learn":[4.226590667],"iteration":300,"passed_time":0.2001858682,"remaining_time":0.4648834614},
{"learn":[4.224038111],"iteration":301,"passed_time":0.2005632904,"remaining_time":0.4635535653},
{"learn":[4.221030448],"iteration":302,"passed_time":0.2009888801,"remaining_time":0.4623407571},
{"learn":[4.219954194],"iteration":303,"passed_time":0.2016585149,"remaining_time":0.4616918631},
{"learn":[4.217940969],"iteration":304,"passed_time":0.202386359,"remaining_time":0.4611754738},
{"learn":[4.215386885],"iteration":305,"passed_time":0.2028305739,"remaining_time":0.4600144388},
{"learn":[4.213602937],"iteration":306,"passed_time":0.2040288832,"remaining_time":0.4605603129},
{"learn":[4.207403817],"iteration":307,"passed_time":0.2044322225,"remaining_time":0.4593087596},
{"learn":[4.200920756],"iteration":308,"passed_time":0.2055841561,"remaining_time":0.4597367375},
{"learn":[4.199149777],"iteration":309,"passed_time":0.2063409173,"remaining_time":0.459274945},
{"learn":[4.197236927],"iteration":310,"passed_time":0.2076922706,"remaining_time":0.4601285351},
{"learn":[4.192042055],"iteration":311,"passed_time":0.2085291579,"remaining_time":0.4598335277},
{"learn":[4.188330937],"iteration":312,"passed_time":0.2089632893,"remaining_time":0.4586510535},
{"learn":[4.183428501],"iteration":313,"passed_time":0.2101628903,"remaining_time":0.4591456776},
{"learn":[4.180425793],"iteration":314,"passed_time":0.2127059278,"remaining_time":0.4625509859},
{"learn":[4.175947559],"iteration":315,"passed_time":0.2149614611,"remaining_time":0.4652963271},
{"learn":[4.170413259],"iteration":316,"passed_time":0.2154116344,"remaining_time":0.4641203353},
{"learn":[4.163842924],"iteration":317,"passed_time":0.2160512688,"remaining_time":0.4633552369},
{"learn":[4.158773124],"iteration":318,"passed_time":0.2170375333,"remaining_time":0.4633309097},
{"learn":[4.155103269],"iteration":319,"passed_time":0.2174096638,"remaining_time":0.4619955356},
{"learn":[4.15106859],"iteration":320,"passed_time":0.2177499605,"remaining_time":0.4605988261},
{"learn":[4.145539208],"iteration":321,"passed_time":0.2182455928,"remaining_time":0.4595357513},
{"learn":[4.144610335],"iteration":322,"passed_time":0.2194274019,"remaining_time":0.4599143997},
{"learn":[4.140423428],"iteration":323,"passed_time":0.2209004236,"remaining_time":0.4608910073},
{"learn":[4.136575459],"iteration":324,"passed_time":0.2221910677,"remaining_time":0.4614737559},
{"learn":[4.135596237],"iteration":325,"passed_time":0.2283788256,"remaining_time":0.4721697191},
{"learn":[4.133233787],"iteration":326,"passed_time":0.2298721809,"remaining_time":0.4731008494},
{"learn":[4.127969869],"iteration":327,"passed_time":0.2316339986,"remaining_time":0.4745672166},
{"learn":[4.121543753],"iteration":328,"passed_time":0.2326964309,"remaining_time":0.4745875536},
{"learn":[4.118646154],"iteration":329,"passed_time":0.2346365845,"remaining_time":0.4763833685},
{"learn":[4.113130027],"iteration":330,"passed_time":0.2361163146,"remaining_time":0.4772260257},
{"learn":[4.108317425],"iteration":331,"passed_time":0.2366991149,"remaining_time":0.4762500264},
{"learn":[4.106041131],"iteration":332,"passed_time":0.2374383758,"remaining_time":0.4755897798},
{"learn":[4.105378649],"iteration":333,"passed_time":0.2390240242,"remaining_time":0.4766167668},
{"learn":[4.099626812],"iteration":334,"passed_time":0.2403603772,"remaining_time":0.4771332861},
{"learn":[4.096445622],"iteration":335,"passed_time":0.2409397191,"remaining_time":0.4761427782},
{"learn":[4.093890188],"iteration":336,"passed_time":0.2414275596,"remaining_time":0.4749746944},
{"learn":[4.091797661],"iteration":337,"passed_time":0.2429469154,"remaining_time":0.4758309407},
{"learn":[4.086511992],"iteration":338,"passed_time":0.2438753874,"remaining_time":0.4755210356},
{"learn":[4.084548389],"iteration":339,"passed_time":0.2464586338,"remaining_time":0.4784197009},
{"learn":[4.079193063],"iteration":340,"passed_time":0.2507209466,"remaining_time":0.4845310963},
{"learn":[4.074973081],"iteration":341,"passed_time":0.2680979528,"remaining_time":0.51581419},
{"learn":[4.070426244],"iteration":342,"passed_time":0.2775804677,"remaining_time":0.5316920328},
{"learn":[4.068919907],"iteration":343,"passed_time":0.2827690858,"remaining_time":0.5392340706},
{"learn":[4.063557628],"iteration":344,"passed_time":0.283546389,"remaining_time":0.5383272022},
{"learn":[4.060037336],"iteration":345,"passed_time":0.2843842346,"remaining_time":0.5375355187},
{"learn":[4.055491427],"iteration":346,"passed_time":0.2848738669,"remaining_time":0.5360882855},
{"learn":[4.054741922],"iteration":347,"passed_time":0.2854118331,"remaining_time":0.5347371126},
{"learn":[4.053143742],"iteration":348,"passed_time":0.2895123102,"remaining_time":0.5400358567},
{"learn":[4.050477011],"iteration":349,"passed_time":0.3469287401,"remaining_time":0.6442962317},
{"learn":[4.044345768],"iteration":350,"passed_time":0.357072598,"remaining_time":0.6602282511},
{"learn":[4.040877925],"iteration":351,"passed_time":0.3594326745,"remaining_time":0.661682878},
{"learn":[4.037402216],"iteration":352,"passed_time":0.3600887675,"remaining_time":0.6599927268},
{"learn":[4.03260517],"iteration":353,"passed_time":0.3617022496,"remaining_time":0.6600555177},
{"learn":[4.028099974],"iteration":354,"passed_time":0.364302913,"remaining_time":0.6619024757},
{"learn":[4.027389855],"iteration":355,"passed_time":0.3649659644,"remaining_time":0.6602193289},
{"learn":[4.023108276],"iteration":356,"passed_time":0.3660532721,"remaining_time":0.6593060335},
{"learn":[4.017252043],"iteration":357,"passed_time":0.3665769465,"remaining_time":0.6573810046},
{"learn":[4.015147944],"iteration":358,"passed_time":0.3672039557,"remaining_time":0.6556482887},
{"learn":[4.014193642],"iteration":359,"passed_time":0.3678742156,"remaining_time":0.6539986055},
{"learn":[4.009833033],"iteration":360,"passed_time":0.3685579757,"remaining_time":0.6523782451},
{"learn":[4.005634268],"iteration":361,"passed_time":0.369867245,"remaining_time":0.651865476},
{"learn":[4.005270769],"iteration":362,"passed_time":0.370496671,"remaining_time":0.6501553151},
{"learn":[4.000998107],"iteration":363,"passed_time":0.3724567415,"remaining_time":0.6507760649},
{"learn":[3.997661264],"iteration":364,"passed_time":0.3745341471,"remaining_time":0.6515868039},
{"learn":[3.995083014],"iteration":365,"passed_time":0.3752202406,"remaining_time":0.6499716736},
{"learn":[3.988692007],"iteration":366,"passed_time":0.3781330335,"remaining_time":0.6522022077},
{"learn":[3.985859367],"iteration":367,"passed_time":0.3786945418,"remaining_time":0.6503667131},
{"learn":[3.982863628],"iteration":368,"passed_time":0.3792399249,"remaining_time":0.648510549},
{"learn":[3.97827523],"iteration":369,"passed_time":0.38060757,"remaining_time":0.6480615382},
{"learn":[3.977413401],"iteration":370,"passed_time":0.3812961218,"remaining_time":0.6464562281},
{"learn":[3.974799943],"iteration":371,"passed_time":0.381984007,"remaining_time":0.6448547215},
{"learn":[3.970279305],"iteration":372,"passed_time":0.3829893968,"remaining_time":0.6437918279},
{"learn":[3.967686339],"iteration":373,"passed_time":0.3845537532,"remaining_time":0.6436648383},
{"learn":[3.965147194],"iteration":374,"passed_time":0.3852595136,"remaining_time":0.6420991894},
{"learn":[3.960060995],"iteration":375,"passed_time":0.3859057315,"remaining_time":0.640439299},
{"learn":[3.959485733],"iteration":376,"passed_time":0.3864260308,"remaining_time":0.6385767034},
{"learn":[3.956167495],"iteration":377,"passed_time":0.3871995006,"remaining_time":0.6371378025},
{"learn":[3.950015],"iteration":378,"passed_time":0.3878504268,"remaining_time":0.6355016228},
{"learn":[3.949682774],"iteration":379,"passed_time":0.3885224784,"remaining_time":0.6339050963},
{"learn":[3.947576179],"iteration":380,"passed_time":0.3912141014,"remaining_time":0.6355945637},
{"learn":[3.944873736],"iteration":381,"passed_time":0.3917721096,"remaining_time":0.6338093292},
{"learn":[3.94102849],"iteration":382,"passed_time":0.3931543384,"remaining_time":0.6333582944},
{"learn":[3.939695464],"iteration":383,"passed_time":0.393877099,"remaining_time":0.631844513},
{"learn":[3.934831797],"iteration":384,"passed_time":0.394329689,"remaining_time":0.6299032695},
{"learn":[3.930411818],"iteration":385,"passed_time":0.3949414064,"remaining_time":0.6282228588},
{"learn":[3.925571988],"iteration":386,"passed_time":0.3956475001,"remaining_time":0.6266974614},
{"learn":[3.923001225],"iteration":387,"passed_time":0.3962682593,"remaining_time":0.6250416873},
{"learn":[3.922680579],"iteration":388,"passed_time":0.3967626416,"remaining_time":0.6231927352},
{"learn":[3.918947641],"iteration":389,"passed_time":0.3976018206,"remaining_time":0.6218900271},
{"learn":[3.916979478],"iteration":390,"passed_time":0.398146537,"remaining_time":0.6201310512},
{"learn":[3.912679716],"iteration":391,"passed_time":0.3988262136,"remaining_time":0.6185875967},
{"learn":[3.909506294],"iteration":392,"passed_time":0.3997091433,"remaining_time":0.6173624682},
{"learn":[3.904902964],"iteration":393,"passed_time":0.4002599431,"remaining_time":0.6156282374},
{"learn":[3.899649563],"iteration":394,"passed_time":0.4007630339,"remaining_time":0.6138269253},
{"learn":[3.898984248],"iteration":395,"passed_time":0.4012182489,"remaining_time":0.6119591473},
{"learn":[3.895192135],"iteration":396,"passed_time":0.4016083797,"remaining_time":0.6099996296},
{"learn":[3.894932298],"iteration":397,"passed_time":0.4020685531,"remaining_time":0.6081539422},
{"learn":[3.892209758],"iteration":398,"passed_time":0.4026568118,"remaining_time":0.60650813},
{"learn":[3.890417474],"iteration":399,"passed_time":0.4030866098,"remaining_time":0.6046299147},
{"learn":[3.886306162],"iteration":400,"passed_time":0.4036605349,"remaining_time":0.6029742155},
{"learn":[3.884833429],"iteration":401,"passed_time":0.4041487088,"remaining_time":0.6011963379},
{"learn":[3.880162018],"iteration":402,"passed_time":0.404683925,"remaining_time":0.599494549},
{"learn":[3.876712647],"iteration":403,"passed_time":0.4057868579,"remaining_time":0.5986360578},
{"learn":[3.871848573],"iteration":404,"passed_time":0.4077279282,"remaining_time":0.599007697},
{"learn":[3.867404435],"iteration":405,"passed_time":0.4089831134,"remaining_time":0.5983644565},
{"learn":[3.86348129],"iteration":406,"passed_time":0.409771875,"remaining_time":0.5970386287},
{"learn":[3.859762038],"iteration":407,"passed_time":0.4103193831,"remaining_time":0.5953653794},
{"learn":[3.854758667],"iteration":408,"passed_time":0.4109348505,"remaining_time":0.5937958353},
{"learn":[3.851940646],"iteration":409,"passed_time":0.4114204827,"remaining_time":0.5920441092},
{"learn":[3.850198694],"iteration":410,"passed_time":0.411870281,"remaining_time":0.590247191},
{"learn":[3.849940469],"iteration":411,"passed_time":0.4122186194,"remaining_time":0.5883120103},
{"learn":[3.84551143],"iteration":412,"passed_time":0.4126615843,"remaining_time":0.5865190072},
{"learn":[3.841373975],"iteration":413,"passed_time":0.4131091742,"remaining_time":0.5847390727},
{"learn":[3.838153644],"iteration":414,"passed_time":0.4134777213,"remaining_time":0.5828541373},
{"learn":[3.833609437],"iteration":415,"passed_time":0.4138632687,"remaining_time":0.581000358},
{"learn":[3.830483469],"iteration":416,"passed_time":0.4142236907,"remaining_time":0.5791184932},
{"learn":[3.82547488],"iteration":417,"passed_time":0.4145715291,"remaining_time":0.5772263874},
{"learn":[3.822896853],"iteration":418,"passed_time":0.4149925353,"remaining_time":0.5754431099},
{"learn":[3.821663286],"iteration":419,"passed_time":0.4154052081,"remaining_time":0.5736548112},
{"learn":[3.817542813],"iteration":420,"passed_time":0.4157498798,"remaining_time":0.5717795259},
{"learn":[3.813567552],"iteration":421,"passed_time":0.4161205103,"remaining_time":0.5699470497},
{"learn":[3.809856606],"iteration":422,"passed_time":0.4165260163,"remaining_time":0.5681690577},
{"learn":[3.807696593],"iteration":423,"passed_time":0.4169508559,"remaining_time":0.5664238042},
{"learn":[3.801960024],"iteration":424,"passed_time":0.4173321532,"remaining_time":0.5646258543},
{"learn":[3.797875497],"iteration":425,"passed_time":0.4177074087,"remaining_time":0.5628264145},
{"learn":[3.796784218],"iteration":426,"passed_time":0.4180282051,"remaining_time":0.5609605656},
{"learn":[3.790504674],"iteration":427,"passed_time":0.4183959188,"remaining_time":0.5591646392},
{"learn":[3.788759035],"iteration":428,"passed_time":0.4187490907,"remaining_time":0.5573560159},
{"learn":[3.786827807],"iteration":429,"passed_time":0.4191421382,"remaining_time":0.5556070204},
{"learn":[3.786106729],"iteration":430,"passed_time":0.4195753529,"remaining_time":0.5539173452},
{"learn":[3.782560718],"iteration":431,"passed_time":0.4200528183,"remaining_time":0.5522916685},
{"learn":[3.781500984],"iteration":432,"passed_time":0.4204784912,"remaining_time":0.5506034746},
{"learn":[3.779082805],"iteration":433,"passed_time":0.4209234978,"remaining_time":0.5489463128},
{"learn":[3.774596632],"iteration":434,"passed_time":0.421663717,"remaining_time":0.5476781612},
{"learn":[3.77145831],"iteration":435,"passed_time":0.4221418907,"remaining_time":0.546073455},
{"learn":[3.770274138],"iteration":436,"passed_time":0.422565272,"remaining_time":0.5444033138},
{"learn":[3.766515776],"iteration":437,"passed_time":0.4229452776,"remaining_time":0.5426832101},
{"learn":[3.76490937],"iteration":438,"passed_time":0.4233492419,"remaining_time":0.5409998285},
{"learn":[3.761761577],"iteration":439,"passed_time":0.4238067486,"remaining_time":0.5393904073},
{"learn":[3.75682723],"iteration":440,"passed_time":0.4241544621,"remaining_time":0.5376470392},
{"learn":[3.753104784],"iteration":441,"passed_time":0.424558843,"remaining_time":0.5359815258},
{"learn":[3.751364214],"iteration":442,"passed_time":0.4249774742,"remaining_time":0.5343396233},
{"learn":[3.74821908],"iteration":443,"passed_time":0.4255182322,"remaining_time":0.5328561646},
{"learn":[3.744544874],"iteration":444,"passed_time":0.4259304049,"remaining_time":0.5312165724},
{"learn":[3.740221742],"iteration":445,"passed_time":0.4263499528,"remaining_time":0.5295916454},
{"learn":[3.738597731],"iteration":446,"passed_time":0.4268104596,"remaining_time":0.5280227833},
{"learn":[3.738261926],"iteration":447,"passed_time":0.4272035904,"remaining_time":0.5263758524},
{"learn":[3.736168491],"iteration":448,"passed_time":0.4276065963,"remaining_time":0.5247466249},
{"learn":[3.733291661],"iteration":449,"passed_time":0.4280306442,"remaining_time":0.5231485652},
{"learn":[3.728580474],"iteration":450,"passed_time":0.4285151097,"remaining_time":0.5216292577},
{"learn":[3.724959866],"iteration":451,"passed_time":0.4289734915,"remaining_time":0.5200829056},
{"learn":[3.722317627],"iteration":452,"passed_time":0.4294152897,"remaining_time":0.5185213321},
{"learn":[3.719455768],"iteration":453,"passed_time":0.4302628438,"remaining_time":0.5174526712},
{"learn":[3.716220645],"iteration":454,"passed_time":0.4308789779,"remaining_time":0.5161077867},
{"learn":[3.709363836],"iteration":455,"passed_time":0.4312908173,"remaining_time":0.5145223785},
{"learn":[3.708426502],"iteration":456,"passed_time":0.4316727813,"remaining_time":0.5129066088},
{"learn":[3.704217865],"iteration":457,"passed_time":0.4320813706,"remaining_time":0.5113277355},
{"learn":[3.701138289],"iteration":458,"passed_time":0.4325153354,"remaining_time":0.5097838702},
{"learn":[3.696580518],"iteration":459,"passed_time":0.4329301331,"remaining_time":0.5082223302},
{"learn":[3.693323331],"iteration":460,"passed_time":0.4333195972,"remaining_time":0.5066361451},
{"learn":[3.689037121],"iteration":461,"passed_time":0.4336520605,"remaining_time":0.504988763},
{"learn":[3.686016993],"iteration":462,"passed_time":0.4341212757,"remaining_time":0.5035056697},
{"learn":[3.685138612],"iteration":463,"passed_time":0.4348621616,"remaining_time":0.5023407729},
{"learn":[3.683295802],"iteration":464,"passed_time":0.4353753359,"remaining_time":0.500915709},
{"learn":[3.682373733],"iteration":465,"passed_time":0.43870851,"remaining_time":0.5027260608},
{"learn":[3.678880759],"iteration":466,"passed_time":0.4394117704,"remaining_time":0.5015127915},
{"learn":[3.675779539],"iteration":467,"passed_time":0.4400137376,"remaining_time":0.5001865564},
{"learn":[3.674622507],"iteration":468,"passed_time":0.4409575015,"remaining_time":0.4992503908},
{"learn":[3.673952954],"iteration":469,"passed_time":0.4414046331,"remaining_time":0.4977541607},
{"learn":[3.672043304],"iteration":470,"passed_time":0.4418820151,"remaining_time":0.4962963609},
{"learn":[3.671413135],"iteration":471,"passed_time":0.4422966046,"remaining_time":0.4947724729},
{"learn":[3.670873631],"iteration":472,"passed_time":0.4428364042,"remaining_time":0.4933927802},
{"learn":[3.670668045],"iteration":473,"passed_time":0.4432162015,"remaining_time":0.4918390759},
{"learn":[3.6704766],"iteration":474,"passed_time":0.4437125838,"remaining_time":0.4904191716},
{"learn":[3.666341249],"iteration":475,"passed_time":0.4442079661,"remaining_time":0.4890020467},
{"learn":[3.664498458],"iteration":476,"passed_time":0.4446148888,"remaining_time":0.4874917963},
{"learn":[3.661391387],"iteration":477,"passed_time":0.4449799358,"remaining_time":0.485940432},
{"learn":[3.656283286],"iteration":478,"passed_time":0.4453264409,"remaining_time":0.4843738533},
{"learn":[3.654793959],"iteration":479,"passed_time":0.4456892379,"remaining_time":0.4828300078},
{"learn":[3.652003879],"iteration":480,"passed_time":0.4461089524,"remaining_time":0.4813524872},
{"learn":[3.65043566],"iteration":481,"passed_time":0.4464602493,"remaining_time":0.4798058281},
{"learn":[3.648284747],"iteration":482,"passed_time":0.4468388382,"remaining_time":0.478293332},
{"learn":[3.644100894],"iteration":483,"passed_time":0.4477999774,"remaining_time":0.4774065875},
{"learn":[3.640430883],"iteration":484,"passed_time":0.4481423574,"remaining_time":0.4758625033},
{"learn":[3.638311292],"iteration":485,"passed_time":0.4485506968,"remaining_time":0.4743931238},
{"learn":[3.636611563],"iteration":486,"passed_time":0.4491190385,"remaining_time":0.4730966463},
{"learn":[3.632682104],"iteration":487,"passed_time":0.4499994681,"remaining_time":0.4721305895},
{"learn":[3.629772412],"iteration":488,"passed_time":0.4508392722,"remaining_time":0.4711224296},
{"learn":[3.62936773],"iteration":489,"passed_time":0.4512940289,"remaining_time":0.4697141933},
{"learn":[3.628977867],"iteration":490,"passed_time":0.4517574107,"remaining_time":0.4683187822},
{"learn":[3.626606495],"iteration":491,"passed_time":0.4523117939,"remaining_time":0.4670211205},
{"learn":[3.62187738],"iteration":492,"passed_time":0.4527275917,"remaining_time":0.4655839533},
{"learn":[3.615612259],"iteration":493,"passed_time":0.4532437243,"remaining_time":0.4642536933},
{"learn":[3.612918905],"iteration":494,"passed_time":0.4537346482,"remaining_time":0.4629010047},
{"learn":[3.61146481],"iteration":495,"passed_time":0.4541549877,"remaining_time":0.4614800682},
{"learn":[3.605505739],"iteration":496,"passed_time":0.4546140362,"remaining_time":0.4601023344},
{"learn":[3.601811253],"iteration":497,"passed_time":0.4551647526,"remaining_time":0.4588206944},
{"learn":[3.600741651],"iteration":498,"passed_time":0.4555853005,"remaining_time":0.4574112937},
{"learn":[3.59722097],"iteration":499,"passed_time":0.4559413891,"remaining_time":0.4559413891},
{"learn":[3.597034975],"iteration":500,"passed_time":0.4563955624,"remaining_time":0.4545736241},
{"learn":[3.594730106],"iteration":501,"passed_time":0.4567851932,"remaining_time":0.4531454705},
{"learn":[3.593520177],"iteration":502,"passed_time":0.4571301566,"remaining_time":0.4516773118},
{"learn":[3.590508187],"iteration":503,"passed_time":0.4574909119,"remaining_time":0.4502291514},
{"learn":[3.588235695],"iteration":504,"passed_time":0.4578747926,"remaining_time":0.448807965},
{"learn":[3.582292826],"iteration":505,"passed_time":0.4582792152,"remaining_time":0.4474109334},
{"learn":[3.58180871],"iteration":506,"passed_time":0.4586746794,"remaining_time":0.4460091064},
{"learn":[3.578272787],"iteration":507,"passed_time":0.4591546865,"remaining_time":0.4446931215},
{"learn":[3.577788665],"iteration":508,"passed_time":0.4595570257,"remaining_time":0.4433055003},
{"learn":[3.574603652],"iteration":509,"passed_time":0.4599406564,"remaining_time":0.4419037679},
{"learn":[3.574419032],"iteration":510,"passed_time":0.4606473751,"remaining_time":0.4408151985},
{"learn":[3.572542867],"iteration":511,"passed_time":0.46108709,"remaining_time":0.4394736326},
{"learn":[3.568560486],"iteration":512,"passed_time":0.461608556,"remaining_time":0.4382131906},
{"learn":[3.568361735],"iteration":513,"passed_time":0.4647397688,"remaining_time":0.4394232055},
{"learn":[3.564310794],"iteration":514,"passed_time":0.4652909853,"remaining_time":0.438186656},
{"learn":[3.562524757],"iteration":515,"passed_time":0.4675068096,"remaining_time":0.4385141392},
{"learn":[3.560721278],"iteration":516,"passed_time":0.4680569011,"remaining_time":0.4372755961},
{"learn":[3.558132267],"iteration":517,"passed_time":0.4684561153,"remaining_time":0.4358993196},
{"learn":[3.553297798],"iteration":518,"passed_time":0.4693463784,"remaining_time":0.4349819037},
{"learn":[3.548040524],"iteration":519,"passed_time":0.4699088034,"remaining_time":0.4337619723},
{"learn":[3.544420237],"iteration":520,"passed_time":0.4703732269,"remaining_time":0.4324544639},
{"learn":[3.543199236],"iteration":521,"passed_time":0.4707360656,"remaining_time":0.4310571635},
{"learn":[3.540016104],"iteration":522,"passed_time":0.4711210712,"remaining_time":0.4296840363},
{"learn":[3.537640948],"iteration":523,"passed_time":0.4715302023,"remaining_time":0.4283365959},
{"learn":[3.535123127],"iteration":524,"passed_time":0.4725178835,"remaining_time":0.4275161803},
{"learn":[3.532885503],"iteration":525,"passed_time":0.4730376412,"remaining_time":0.4262734637},
{"learn":[3.532538156],"iteration":526,"passed_time":0.4734378137,"remaining_time":0.4249261592},
{"learn":[3.5293643],"iteration":527,"passed_time":0.4738910287,"remaining_time":0.423629859},
{"learn":[3.52813781],"iteration":528,"passed_time":0.4743217851,"remaining_time":0.42231675},
{"learn":[3.526244674],"iteration":529,"passed_time":0.4749526694,"remaining_time":0.4211844427},
{"learn":[3.523907057],"iteration":530,"passed_time":0.4753907592,"remaining_time":0.4198837402},
{"learn":[3.521123331],"iteration":531,"passed_time":0.4757951818,"remaining_time":0.4185566637},
{"learn":[3.518752355],"iteration":532,"passed_time":0.4762296466,"remaining_time":0.4172593714},
{"learn":[3.516434738],"iteration":533,"passed_time":0.4766201523,"remaining_time":0.4159269494},
{"learn":[3.512637838],"iteration":534,"passed_time":0.4771231597,"remaining_time":0.4146958304},
{"learn":[3.509899326],"iteration":535,"passed_time":0.4807806303,"remaining_time":0.4161981576},
{"learn":[3.509735749],"iteration":536,"passed_time":0.4819189388,"remaining_time":0.4155092526},
{"learn":[3.505517292],"iteration":537,"passed_time":0.4823008611,"remaining_time":0.4141691409},
{"learn":[3.503304909],"iteration":538,"passed_time":0.4828017434,"remaining_time":0.4129343297},
{"learn":[3.501805587],"iteration":539,"passed_time":0.4832595419,"remaining_time":0.4116655357},
{"learn":[3.498871117],"iteration":540,"passed_time":0.4836492559,"remaining_time":0.410341975},
{"learn":[3.496018266],"iteration":541,"passed_time":0.4840061779,"remaining_time":0.4089941503},
{"learn":[3.493537825],"iteration":542,"passed_time":0.4844338925,"remaining_time":0.4077095559},
{"learn":[3.491382894],"iteration":543,"passed_time":0.4849201914,"remaining_time":0.4064772192},
{"learn":[3.48756175],"iteration":544,"passed_time":0.4861506678,"remaining_time":0.4058689062},
{"learn":[3.485523232],"iteration":545,"passed_time":0.4867067594,"remaining_time":0.4046975618},
{"learn":[3.482609155],"iteration":546,"passed_time":0.4875791472,"remaining_time":0.4037904089},
{"learn":[3.478969388],"iteration":547,"passed_time":0.4883994926,"remaining_time":0.4028404574},
{"learn":[3.476511488],"iteration":548,"passed_time":0.4911083243,"remaining_time":0.4034423574},
{"learn":[3.473705198],"iteration":549,"passed_time":0.4917047914,"remaining_time":0.4023039202},
{"learn":[3.468363611],"iteration":550,"passed_time":0.4924245937,"remaining_time":0.4012679538},
{"learn":[3.466496761],"iteration":551,"passed_time":0.4929510598,"remaining_time":0.4000762224},
{"learn":[3.463608519],"iteration":552,"passed_time":0.4936334448,"remaining_time":0.3990129292},
{"learn":[3.463181263],"iteration":553,"passed_time":0.4940988683,"remaining_time":0.3977763453},
{"learn":[3.463053629],"iteration":554,"passed_time":0.4946540015,"remaining_time":0.3966144697},
{"learn":[3.460551709],"iteration":555,"passed_time":0.4950491324,"remaining_time":0.395327005},
{"learn":[3.457864056],"iteration":556,"passed_time":0.495429388,"remaining_time":0.3940309136},
{"learn":[3.457485714],"iteration":557,"passed_time":0.4957923517,"remaining_time":0.3927244076},
{"learn":[3.455143229],"iteration":558,"passed_time":0.496451528,"remaining_time":0.3916549622},
{"learn":[3.451155129],"iteration":559,"passed_time":0.4970442034,"remaining_time":0.3905347313},
{"learn":[3.449245251],"iteration":560,"passed_time":0.4976741294,"remaining_time":0.3894455308},
{"learn":[3.444586466],"iteration":561,"passed_time":0.4980249679,"remaining_time":0.3881404554},
{"learn":[3.44220798],"iteration":562,"passed_time":0.4983368058,"remaining_time":0.3868084976},
{"learn":[3.438375295],"iteration":563,"passed_time":0.4987921459,"remaining_time":0.3855910915},
{"learn":[3.438144708],"iteration":564,"passed_time":0.4992034019,"remaining_time":0.3843424422},
{"learn":[3.435068915],"iteration":565,"passed_time":0.4995641573,"remaining_time":0.3830580287},
{"learn":[3.434148912],"iteration":566,"passed_time":0.4999004956,"remaining_time":0.3817582268},
{"learn":[3.430138319],"iteration":567,"passed_time":0.5003155017,"remaining_time":0.3805216492},
{"learn":[3.428513345],"iteration":568,"passed_time":0.5006610068,"remaining_time":0.3792353144},
{"learn":[3.424095562],"iteration":569,"passed_time":0.5012218067,"remaining_time":0.3781146963},
{"learn":[3.4214375],"iteration":570,"passed_time":0.5016244793,"remaining_time":0.3768772358},
{"learn":[3.419493677],"iteration":571,"passed_time":0.5020470689,"remaining_time":0.375657597},
{"learn":[3.415073914],"iteration":572,"passed_time":0.5024543249,"remaining_time":0.3744293137},
{"learn":[3.414900097],"iteration":573,"passed_time":0.5028984564,"remaining_time":0.3732312586},
{"learn":[3.412598553],"iteration":574,"passed_time":0.5036186337,"remaining_time":0.3722398597},
{"learn":[3.410434407],"iteration":575,"passed_time":0.5040023894,"remaining_time":0.3710017588},
{"learn":[3.406811806],"iteration":576,"passed_time":0.5043112689,"remaining_time":0.3697117275},
{"learn":[3.405303164],"iteration":577,"passed_time":0.5046064816,"remaining_time":0.3684151129},
{"learn":[3.40177936],"iteration":578,"passed_time":0.5049831538,"remaining_time":0.3671811878},
{"learn":[3.400515698],"iteration":579,"passed_time":0.5052921584,"remaining_time":0.3659012181},
{"learn":[3.396038308],"iteration":580,"passed_time":0.5056152881,"remaining_time":0.3646347775},
{"learn":[3.394483342],"iteration":581,"passed_time":0.5059365012,"remaining_time":0.3633702019},
{"learn":[3.392591264],"iteration":582,"passed_time":0.5062531309,"remaining_time":0.3621055842},
{"learn":[3.390133846],"iteration":583,"passed_time":0.506557552,"remaining_time":0.3608355165},
{"learn":[3.386464198],"iteration":584,"passed_time":0.506850723,"remaining_time":0.3595607693},
{"learn":[3.381246978],"iteration":585,"passed_time":0.5071748528,"remaining_time":0.3583112441},
{"learn":[3.378820461],"iteration":586,"passed_time":0.5074708155,"remaining_time":0.3570450542},
{"learn":[3.375970284],"iteration":587,"passed_time":0.5077830701,"remaining_time":0.3557935797},
{"learn":[3.371408647],"iteration":588,"passed_time":0.5080828245,"remaining_time":0.354536572},
{"learn":[3.368930835],"iteration":589,"passed_time":0.508411871,"remaining_time":0.3533031646},
{"learn":[3.368660374],"iteration":590,"passed_time":0.5087290007,"remaining_time":0.3520645707},
{"learn":[3.366620011],"iteration":591,"passed_time":0.5090860893,"remaining_time":0.3508566291},
{"learn":[3.365180291],"iteration":592,"passed_time":0.5094650949,"remaining_time":0.3496665997},
{"learn":[3.36472719],"iteration":593,"passed_time":0.5097820162,"remaining_time":0.3484368663},
{"learn":[3.362416089],"iteration":594,"passed_time":0.5100658538,"remaining_time":0.347187682},
{"learn":[3.360836826],"iteration":595,"passed_time":0.5104141506,"remaining_time":0.3459854309},
{"learn":[3.357425853],"iteration":596,"passed_time":0.5107480722,"remaining_time":0.3447763368},
{"learn":[3.35457272],"iteration":597,"passed_time":0.5110483266,"remaining_time":0.3435475373},
{"learn":[3.352022549],"iteration":598,"passed_time":0.5113537894,"remaining_time":0.3423253248},
{"learn":[3.349739394],"iteration":599,"passed_time":0.5117051696,"remaining_time":0.3411367797},
{"learn":[3.345955036],"iteration":600,"passed_time":0.5119908821,"remaining_time":0.3399074243},
{"learn":[3.343743184],"iteration":601,"passed_time":0.5123136369,"remaining_time":0.3387056935},
{"learn":[3.340918527],"iteration":602,"passed_time":0.5126617254,"remaining_time":0.3375235572},
{"learn":[3.336649515],"iteration":603,"passed_time":0.5130461477,"remaining_time":0.3363680041},
{"learn":[3.333529795],"iteration":604,"passed_time":0.5133334853,"remaining_time":0.3351516144},
{"learn":[3.329153136],"iteration":605,"passed_time":0.5136234479,"remaining_time":0.3339399975},
{"learn":[3.325509138],"iteration":606,"passed_time":0.5139240773,"remaining_time":0.3327383235},
{"learn":[3.325217634],"iteration":607,"passed_time":0.5142229984,"remaining_time":0.3315385121},
{"learn":[3.323955897],"iteration":608,"passed_time":0.5145071692,"remaining_time":0.3303321891},
{"learn":[3.322459859],"iteration":609,"passed_time":0.5148090487,"remaining_time":0.3291402115},
{"learn":[3.320953504],"iteration":610,"passed_time":0.5151144699,"remaining_time":0.3279534023},
{"learn":[3.320687671],"iteration":611,"passed_time":0.5153940573,"remaining_time":0.3267530952},
{"learn":[3.317996989],"iteration":612,"passed_time":0.5157696879,"remaining_time":0.3256164261},
{"learn":[3.31692827],"iteration":613,"passed_time":0.5161956108,"remaining_time":0.3245138531},
{"learn":[3.315434142],"iteration":614,"passed_time":0.5165293241,"remaining_time":0.3233557557},
{"learn":[3.312502383],"iteration":615,"passed_time":0.5169057879,"remaining_time":0.3222269847},
{"learn":[3.312386899],"iteration":616,"passed_time":0.5172760851,"remaining_time":0.3210968243},
{"learn":[3.309213337],"iteration":617,"passed_time":0.5175786312,"remaining_time":0.3199272445},
{"learn":[3.307438592],"iteration":618,"passed_time":0.5178902608,"remaining_time":0.3187660571},
{"learn":[3.304130432],"iteration":619,"passed_time":0.5181976403,"remaining_time":0.3176050054},
{"learn":[3.303876784],"iteration":620,"passed_time":0.5184623109,"remaining_time":0.3164206374},
{"learn":[3.303026174],"iteration":621,"passed_time":0.5187768155,"remaining_time":0.3152695117},
{"learn":[3.302616639],"iteration":622,"passed_time":0.5190414028,"remaining_time":0.3140908649},
{"learn":[3.299095104],"iteration":623,"passed_time":0.5193294903,"remaining_time":0.3129293083},
{"learn":[3.29721647],"iteration":624,"passed_time":0.5196479117,"remaining_time":0.311788747},
{"learn":[3.295579315],"iteration":625,"passed_time":0.5199427494,"remaining_time":0.3106367225},
{"learn":[3.293233175],"iteration":626,"passed_time":0.5202389204,"remaining_time":0.3094882254},
{"learn":[3.292914216],"iteration":627,"passed_time":0.520661635,"remaining_time":0.3084174016},
{"learn":[3.291475186],"iteration":628,"passed_time":0.5211455171,"remaining_time":0.3073847168},
{"learn":[3.290252231],"iteration":629,"passed_time":0.5215823986,"remaining_time":0.3063261706},
{"learn":[3.288468027],"iteration":630,"passed_time":0.5219052367,"remaining_time":0.3052029038},
{"learn":[3.288308542],"iteration":631,"passed_time":0.5222672837,"remaining_time":0.3041050006},
{"learn":[3.286150082],"iteration":632,"passed_time":0.5227200403,"remaining_time":0.3030620139},
{"learn":[3.285803091],"iteration":633,"passed_time":0.5232047558,"remaining_time":0.3020393385},
{"learn":[3.285699434],"iteration":634,"passed_time":0.5236988464,"remaining_time":0.3010237464},
{"learn":[3.284725694],"iteration":635,"passed_time":0.5242721049,"remaining_time":0.3000551041},
{"learn":[3.281347828],"iteration":636,"passed_time":0.5247399451,"remaining_time":0.2990276296},
{"learn":[3.279431843],"iteration":637,"passed_time":0.5250909503,"remaining_time":0.2979356176},
{"learn":[3.276204828],"iteration":638,"passed_time":0.5254263719,"remaining_time":0.2968371209},
{"learn":[3.273589955],"iteration":639,"passed_time":0.5257187512,"remaining_time":0.2957167976},
{"learn":[3.271785701],"iteration":640,"passed_time":0.5262490924,"remaining_time":0.294732331},
{"learn":[3.271575019],"iteration":641,"passed_time":0.5270393124,"remaining_time":0.293894196},
{"learn":[3.271305494],"iteration":642,"passed_time":0.5273165664,"remaining_time":0.2927714063},
{"learn":[3.270092387],"iteration":643,"passed_time":0.5282493719,"remaining_time":0.2920136279},
{"learn":[3.26895992],"iteration":644,"passed_time":0.5287299623,"remaining_time":0.2910064134},
{"learn":[3.264691395],"iteration":645,"passed_time":0.5296171004,"remaining_time":0.2902236123},
{"learn":[3.262385746],"iteration":646,"passed_time":0.5303668198,"remaining_time":0.2893655137},
{"learn":[3.261094647],"iteration":647,"passed_time":0.5313827514,"remaining_time":0.2886523588},
{"learn":[3.259070383],"iteration":648,"passed_time":0.5317578819,"remaining_time":0.287591705},
{"learn":[3.25629763],"iteration":649,"passed_time":0.5330196505,"remaining_time":0.2870105811},
{"learn":[3.253307878],"iteration":650,"passed_time":0.5335726587,"remaining_time":0.2860474007},
{"learn":[3.250702647],"iteration":651,"passed_time":0.5338968718,"remaining_time":0.284963361},
{"learn":[3.248581889],"iteration":652,"passed_time":0.5342917943,"remaining_time":0.283919223},
{"learn":[3.246223206],"iteration":653,"passed_time":0.5346763833,"remaining_time":0.2828716034},
{"learn":[3.24546099],"iteration":654,"passed_time":0.5350005547,"remaining_time":0.2817941853},
{"learn":[3.243876155],"iteration":655,"passed_time":0.5360331116,"remaining_time":0.2810905341},
{"learn":[3.241899651],"iteration":656,"passed_time":0.5363334077,"remaining_time":0.2800035903},
{"learn":[3.239807589],"iteration":657,"passed_time":0.5368995827,"remaining_time":0.2790572299},
{"learn":[3.239573042],"iteration":658,"passed_time":0.5374161737,"remaining_time":0.2780863661},
{"learn":[3.235787299],"iteration":659,"passed_time":0.5378521384,"remaining_time":0.277075344},
{"learn":[3.233660376],"iteration":660,"passed_time":0.5381971435,"remaining_time":0.2760194125},
{"learn":[3.231377269],"iteration":661,"passed_time":0.5385904827,"remaining_time":0.2749903069},
{"learn":[3.229904888],"iteration":662,"passed_time":0.5389344877,"remaining_time":0.2739380428},
{"learn":[3.226682112],"iteration":663,"passed_time":0.5392296588,"remaining_time":0.2728632008},
{"learn":[3.226390811],"iteration":664,"passed_time":0.53954133,"remaining_time":0.2717990159},
{"learn":[3.225310727],"iteration":665,"passed_time":0.5398590847,"remaining_time":0.2707401416},
{"learn":[3.223569972],"iteration":666,"passed_time":0.5401718393,"remaining_time":0.2696809932},
{"learn":[3.220667701],"iteration":667,"passed_time":0.5405220945,"remaining_time":0.2686427176},
{"learn":[3.218241672],"iteration":668,"passed_time":0.5408250156,"remaining_time":0.2675830795},
{"learn":[3.216464002],"iteration":669,"passed_time":0.5411629789,"remaining_time":0.2665429598},
{"learn":[3.215353439],"iteration":670,"passed_time":0.5415454429,"remaining_time":0.2655267522},
{"learn":[3.214949285],"iteration":671,"passed_time":0.5418617809,"remaining_time":0.264480155},
{"learn":[3.213437915],"iteration":672,"passed_time":0.542206411,"remaining_time":0.2634494746},
{"learn":[3.209633168],"iteration":673,"passed_time":0.5425449576,"remaining_time":0.2624178875},
{"learn":[3.208040583],"iteration":674,"passed_time":0.5429231715,"remaining_time":0.261407453},
{"learn":[3.20594173],"iteration":675,"passed_time":0.5432760101,"remaining_time":0.2603867267},
{"learn":[3.203453937],"iteration":676,"passed_time":0.5436035149,"remaining_time":0.2593558867},
{"learn":[3.202269702],"iteration":677,"passed_time":0.5439079777,"remaining_time":0.2583161782},
{"learn":[3.198305471],"iteration":678,"passed_time":0.5442720248,"remaining_time":0.2573068041},
{"learn":[3.196688395],"iteration":679,"passed_time":0.5446323634,"remaining_time":0.2562975828},
{"learn":[3.1951188],"iteration":680,"passed_time":0.5449874103,"remaining_time":0.2552877884},
{"learn":[3.192875645],"iteration":681,"passed_time":0.5453807078,"remaining_time":0.2542977494},
{"learn":[3.19277753],"iteration":682,"passed_time":0.5457455048,"remaining_time":0.2532962299},
{"learn":[3.19258051],"iteration":683,"passed_time":0.5462871795,"remaining_time":0.2523782876},
{"learn":[3.190121892],"iteration":684,"passed_time":0.5466031008,"remaining_time":0.2513576303},
{"learn":[3.189681053],"iteration":685,"passed_time":0.5471077332,"remaining_time":0.2504254056},
{"learn":[3.189538676],"iteration":686,"passed_time":0.5475823236,"remaining_time":0.2494807384},
{"learn":[3.188933801],"iteration":687,"passed_time":0.5481052063,"remaining_time":0.2485593377},
{"learn":[3.187111582],"iteration":688,"passed_time":0.5484758368,"remaining_time":0.2475703704},
{"learn":[3.185265727],"iteration":689,"passed_time":0.5488897595,"remaining_time":0.2466026456},
{"learn":[3.18278119],"iteration":690,"passed_time":0.5492055975,"remaining_time":0.2455926623},
{"learn":[3.180364493],"iteration":691,"passed_time":0.5495247272,"remaining_time":0.2445861503},
{"learn":[3.178387064],"iteration":692,"passed_time":0.5498050647,"remaining_time":0.243564437},
{"learn":[3.174929696],"iteration":693,"passed_time":0.5501132359,"remaining_time":0.2425571328},
{"learn":[3.171847686],"iteration":694,"passed_time":0.550413657,"remaining_time":0.2415484394},
{"learn":[3.171703217],"iteration":695,"passed_time":0.5507199532,"remaining_time":0.2405443474},
{"learn":[3.169571032],"iteration":696,"passed_time":0.5510752501,"remaining_time":0.2395635592},
{"learn":[3.167638462],"iteration":697,"passed_time":0.5513704211,"remaining_time":0.238558549},
{"learn":[3.165002604],"iteration":698,"passed_time":0.5517248847,"remaining_time":0.237581102},
{"learn":[3.163312767],"iteration":699,"passed_time":0.5520563895,"remaining_time":0.2365955955},
{"learn":[3.161917483],"iteration":700,"passed_time":0.552338102,"remaining_time":0.2355907168},
{"learn":[3.160112936],"iteration":701,"passed_time":0.5526356481,"remaining_time":0.2345946198},
{"learn":[3.15671731],"iteration":702,"passed_time":0.5529202356,"remaining_time":0.2335950355},
{"learn":[3.154578612],"iteration":703,"passed_time":0.55321724,"remaining_time":0.2326027032},
{"learn":[3.154037347],"iteration":704,"passed_time":0.553553495,"remaining_time":0.2316287674},
{"learn":[3.152248757],"iteration":705,"passed_time":0.5538447909,"remaining_time":0.2306379158},
{"learn":[3.149775798],"iteration":706,"passed_time":0.5541371286,"remaining_time":0.2296494748},
{"learn":[3.148387869],"iteration":707,"passed_time":0.554417466,"remaining_time":0.228658051},
{"learn":[3.144489239],"iteration":708,"passed_time":0.5547159704,"remaining_time":0.2276760894},
{"learn":[3.141717509],"iteration":709,"passed_time":0.5550126831,"remaining_time":0.2266953213},
{"learn":[3.140352604],"iteration":710,"passed_time":0.555298604,"remaining_time":0.2257120908},
{"learn":[3.138758655],"iteration":711,"passed_time":0.5556469008,"remaining_time":0.2247560498},
{"learn":[3.136316684],"iteration":712,"passed_time":0.555997031,"remaining_time":0.2238024515},
{"learn":[3.135161339],"iteration":713,"passed_time":0.5563319942,"remaining_time":0.2228444683},
{"learn":[3.134786255],"iteration":714,"passed_time":0.5566309153,"remaining_time":0.2218738614},
{"learn":[3.13335391],"iteration":715,"passed_time":0.5569212946,"remaining_time":0.2209017426},
{"learn":[3.131182765],"iteration":716,"passed_time":0.5572152989,"remaining_time":0.2199329562},
{"learn":[3.127614404],"iteration":717,"passed_time":0.5575183034,"remaining_time":0.2189695843},
{"learn":[3.125022306],"iteration":718,"passed_time":0.5579038091,"remaining_time":0.2180402926},
{"learn":[3.123824804],"iteration":719,"passed_time":0.5582727729,"remaining_time":0.2171060783},
{"learn":[3.121902827],"iteration":720,"passed_time":0.5585863608,"remaining_time":0.2161520037},
{"learn":[3.118384947],"iteration":721,"passed_time":0.5589104906,"remaining_time":0.2152037623},
{"learn":[3.118216259],"iteration":722,"passed_time":0.5592124951,"remaining_time":0.2142487706},
{"learn":[3.116566274],"iteration":723,"passed_time":0.5595196246,"remaining_time":0.2132975364},
{"learn":[3.11419157],"iteration":724,"passed_time":0.5599227555,"remaining_time":0.2123844935},
{"learn":[3.112655366],"iteration":725,"passed_time":0.5602907193,"remaining_time":0.2114595828},
{"learn":[3.110363167],"iteration":726,"passed_time":0.5606006822,"remaining_time":0.210514424},
{"learn":[3.108261505],"iteration":727,"passed_time":0.5609802711,"remaining_time":0.2095970244},
{"learn":[3.107241022],"iteration":728,"passed_time":0.5612756505,"remaining_time":0.208649796},
{"learn":[3.105834465],"iteration":729,"passed_time":0.5616639479,"remaining_time":0.2077387204},
{"learn":[3.104190206],"iteration":730,"passed_time":0.562057162,"remaining_time":0.2068308845},
{"learn":[3.103068647],"iteration":731,"passed_time":0.5624089172,"remaining_time":0.2059092757},
{"learn":[3.101212117],"iteration":732,"passed_time":0.5627501722,"remaining_time":0.204985397},
{"learn":[3.100484004],"iteration":733,"passed_time":0.5631295945,"remaining_time":0.2040769375},
{"learn":[3.097005645],"iteration":734,"passed_time":0.5634678495,"remaining_time":0.203155075},
{"learn":[3.096914148],"iteration":735,"passed_time":0.5638344382,"remaining_time":0.2022449615},
{"learn":[3.095125219],"iteration":736,"passed_time":0.5642382775,"remaining_time":0.201349616},
{"learn":[3.092700318],"iteration":737,"passed_time":0.5646476169,"remaining_time":0.200457555},
{"learn":[3.090239234],"iteration":738,"passed_time":0.5650196223,"remaining_time":0.1995536149},
{"learn":[3.089289627],"iteration":739,"passed_time":0.5653595024,"remaining_time":0.1986398252},
{"learn":[3.088118131],"iteration":740,"passed_time":0.5656711736,"remaining_time":0.1977177247},
{"learn":[3.086285684],"iteration":741,"passed_time":0.565989595,"remaining_time":0.1967996166},
{"learn":[3.084541236],"iteration":742,"passed_time":0.5664204347,"remaining_time":0.1959220077},
{"learn":[3.081527526],"iteration":743,"passed_time":0.5673191562,"remaining_time":0.1952065914},
{"learn":[3.079586746],"iteration":744,"passed_time":0.5676401193,"remaining_time":0.1942929267},
{"learn":[3.079102416],"iteration":745,"passed_time":0.568048292,"remaining_time":0.1934105445},
{"learn":[3.077793533],"iteration":746,"passed_time":0.568409214,"remaining_time":0.1925134286},
{"learn":[3.076588772],"iteration":747,"passed_time":0.568750094,"remaining_time":0.1916109942},
{"learn":[3.074334966],"iteration":748,"passed_time":0.5690779738,"remaining_time":0.1907057029},
{"learn":[3.072050885],"iteration":749,"passed_time":0.5694296874,"remaining_time":0.1898098958},
{"learn":[3.068871201],"iteration":750,"passed_time":0.569763984,"remaining_time":0.188909763},
{"learn":[3.067744797],"iteration":751,"passed_time":0.5702202407,"remaining_time":0.188051356},
{"learn":[3.066417822],"iteration":752,"passed_time":0.5705843711,"remaining_time":0.1871637977},
{"learn":[3.063347838],"iteration":753,"passed_time":0.5710478779,"remaining_time":0.1863100503},
{"learn":[3.059859921],"iteration":754,"passed_time":0.5714528422,"remaining_time":0.1854383395},
{"learn":[3.05816686],"iteration":755,"passed_time":0.5718008057,"remaining_time":0.1845494664},
{"learn":[3.056758574],"iteration":756,"passed_time":0.5721206437,"remaining_time":0.183652994},
{"learn":[3.053807539],"iteration":757,"passed_time":0.5724399401,"remaining_time":0.1827578701},
{"learn":[3.051549081],"iteration":758,"passed_time":0.5727427779,"remaining_time":0.1818590375},
{"learn":[3.050959748],"iteration":759,"passed_time":0.5730595325,"remaining_time":0.1809661682},
{"learn":[3.050596171],"iteration":760,"passed_time":0.5733822456,"remaining_time":0.1800766842},
{"learn":[3.04937852],"iteration":761,"passed_time":0.5736822084,"remaining_time":0.1791815821},
{"learn":[3.04784341],"iteration":762,"passed_time":0.5740079632,"remaining_time":0.1782960515},
{"learn":[3.045508584],"iteration":763,"passed_time":0.5743265096,"remaining_time":0.1774097595},
{"learn":[3.04271586],"iteration":764,"passed_time":0.5746748064,"remaining_time":0.1765340908},
{"learn":[3.041115001],"iteration":765,"passed_time":0.5749642273,"remaining_time":0.1756418136},
{"learn":[3.039665864],"iteration":766,"passed_time":0.5753206492,"remaining_time":0.1747714619},
{"learn":[3.036313248],"iteration":767,"passed_time":0.575782406,"remaining_time":0.1739342685},
{"learn":[3.034743731],"iteration":768,"passed_time":0.5761262028,"remaining_time":0.1730626175},
{"learn":[3.033487619],"iteration":769,"passed_time":0.5765399172,"remaining_time":0.172213222},
{"learn":[3.031382536],"iteration":770,"passed_time":0.5770138409,"remaining_time":0.1713828399},
{"learn":[3.029362291],"iteration":771,"passed_time":0.5774600974,"remaining_time":0.1705452101},
{"learn":[3.028884987],"iteration":772,"passed_time":0.5778348946,"remaining_time":0.1696876081},
{"learn":[3.027474608],"iteration":773,"passed_time":0.5781820247,"remaining_time":0.1688231752},
{"learn":[3.027171613],"iteration":774,"passed_time":0.5785285715,"remaining_time":0.1679599079},
{"learn":[3.02461443],"iteration":775,"passed_time":0.5788370344,"remaining_time":0.167086979},
{"learn":[3.021412728],"iteration":776,"passed_time":0.5794691687,"remaining_time":0.1663083972},
{"learn":[3.019746108],"iteration":777,"passed_time":0.5799148836,"remaining_time":0.1654769976},
{"learn":[3.018764045],"iteration":778,"passed_time":0.5803454733,"remaining_time":0.1646422973},
{"learn":[3.018452541],"iteration":779,"passed_time":0.5809526489,"remaining_time":0.1638584394},
{"learn":[3.018272157],"iteration":780,"passed_time":0.5813736551,"remaining_time":0.1630228303},
{"learn":[3.017152749],"iteration":781,"passed_time":0.5818860794,"remaining_time":0.1622137664},
{"learn":[3.016998898],"iteration":782,"passed_time":0.5823562946,"remaining_time":0.1613937624},
{"learn":[3.01416394],"iteration":783,"passed_time":0.5829486367,"remaining_time":0.1606082979},
{"learn":[3.011753522],"iteration":784,"passed_time":0.5833761013,"remaining_time":0.1597781679},
{"learn":[3.011274639],"iteration":785,"passed_time":0.5837854824,"remaining_time":0.158944139},
{"learn":[3.010881106],"iteration":786,"passed_time":0.5842055302,"remaining_time":0.1581140762},
{"learn":[3.009033266],"iteration":787,"passed_time":0.5846311198,"remaining_time":0.1572865449},
{"learn":[3.008051937],"iteration":788,"passed_time":0.5850437926,"remaining_time":0.1564565782},
{"learn":[3.007402786],"iteration":789,"passed_time":0.5854598404,"remaining_time":0.1556285652},
{"learn":[3.005320643],"iteration":790,"passed_time":0.5869653626,"remaining_time":0.1550894574},
{"learn":[3.005231865],"iteration":791,"passed_time":0.5873751186,"remaining_time":0.1542601322},
{"learn":[3.001976553],"iteration":792,"passed_time":0.5877755412,"remaining_time":0.1534294288},
{"learn":[3.001120495],"iteration":793,"passed_time":0.5883672166,"remaining_time":0.152649429},
{"learn":[2.999376338],"iteration":794,"passed_time":0.5891602699,"remaining_time":0.1519218306},
{"learn":[2.998453311],"iteration":795,"passed_time":0.5895070667,"remaining_time":0.1510797005},
{"learn":[2.996990702],"iteration":796,"passed_time":0.5901807433,"remaining_time":0.1503220714},
{"learn":[2.995519791],"iteration":797,"passed_time":0.5914582622,"remaining_time":0.149717505},
{"learn":[2.994723092],"iteration":798,"passed_time":0.591789767,"remaining_time":0.1488732706},
{"learn":[2.993519754],"iteration":799,"passed_time":0.5921342305,"remaining_time":0.1480335576},
{"learn":[2.992888758],"iteration":800,"passed_time":0.5924611936,"remaining_time":0.1471907335},
{"learn":[2.991198829],"iteration":801,"passed_time":0.5928006986,"remaining_time":0.1463522922},
{"learn":[2.988138075],"iteration":802,"passed_time":0.5931397036,"remaining_time":0.1455149709},
{"learn":[2.985253723],"iteration":803,"passed_time":0.5934616667,"remaining_time":0.1446747347},
{"learn":[2.983228826],"iteration":804,"passed_time":0.5937671712,"remaining_time":0.1438317992},
{"learn":[2.982660555],"iteration":805,"passed_time":0.5940747174,"remaining_time":0.1429906888},
{"learn":[2.981559172],"iteration":806,"passed_time":0.5944172224,"remaining_time":0.1421592614},
{"learn":[2.981153849],"iteration":807,"passed_time":0.5947344355,"remaining_time":0.1413230342},
{"learn":[2.980189169],"iteration":808,"passed_time":0.5950507318,"remaining_time":0.1404878736},
{"learn":[2.978896532],"iteration":809,"passed_time":0.5954053203,"remaining_time":0.1396629764},
{"learn":[2.978026123],"iteration":810,"passed_time":0.5957537838,"remaining_time":0.1388378115},
{"learn":[2.975290118],"iteration":811,"passed_time":0.596150748,"remaining_time":0.13802505},
{"learn":[2.97490312],"iteration":812,"passed_time":0.5964914197,"remaining_time":0.1372003634},
{"learn":[2.971211834],"iteration":813,"passed_time":0.5968183412,"remaining_time":0.1363737242},
{"learn":[2.971173966],"iteration":814,"passed_time":0.5970653865,"remaining_time":0.1355301798},
{"learn":[2.970827203],"iteration":815,"passed_time":0.5973624742,"remaining_time":0.1346993814},
{"learn":[2.969457975],"iteration":816,"passed_time":0.5977297713,"remaining_time":0.1338856158},
{"learn":[2.968405068],"iteration":817,"passed_time":0.5981450274,"remaining_time":0.1330836125},
{"learn":[2.967317156],"iteration":818,"passed_time":0.5985181579,"remaining_time":0.1322732437},
{"learn":[2.965675525],"iteration":819,"passed_time":0.5988820383,"remaining_time":0.1314619108},
{"learn":[2.963812019],"iteration":820,"passed_time":0.5992199599,"remaining_time":0.1306460083},
{"learn":[2.96152609],"iteration":821,"passed_time":0.599607549,"remaining_time":0.129842024},
{"learn":[2.961351375],"iteration":822,"passed_time":0.5999656376,"remaining_time":0.129032707},
{"learn":[2.961182754],"iteration":823,"passed_time":0.6003438932,"remaining_time":0.1282287927},
{"learn":[2.958969609],"iteration":824,"passed_time":0.6006874399,"remaining_time":0.1274185479},
{"learn":[2.957174394],"iteration":825,"passed_time":0.6010025279,"remaining_time":0.1266034381},
{"learn":[2.956281471],"iteration":826,"passed_time":0.6013260326,"remaining_time":0.1257912982},
{"learn":[2.954690335],"iteration":827,"passed_time":0.6017379137,"remaining_time":0.1249986971},
{"learn":[2.953877073],"iteration":828,"passed_time":0.602142378,"remaining_time":0.1242054845},
{"learn":[2.952359725],"iteration":829,"passed_time":0.6025202586,"remaining_time":0.1234077638},
{"learn":[2.952229302],"iteration":830,"passed_time":0.6029600984,"remaining_time":0.1226236542},
{"learn":[2.951626668],"iteration":831,"passed_time":0.603339729,"remaining_time":0.1218282145},
{"learn":[2.950424935],"iteration":832,"passed_time":0.6037010677,"remaining_time":0.121030106},
{"learn":[2.949560927],"iteration":833,"passed_time":0.6040229057,"remaining_time":0.1202251827},
{"learn":[2.948544617],"iteration":834,"passed_time":0.6044533704,"remaining_time":0.1194428816},
{"learn":[2.947513434],"iteration":835,"passed_time":0.6048234592,"remaining_time":0.1186495781},
{"learn":[2.946182815],"iteration":836,"passed_time":0.6052832993,"remaining_time":0.1178747644},
{"learn":[2.945976414],"iteration":837,"passed_time":0.6056497631,"remaining_time":0.1170826511},
{"learn":[2.944573286],"iteration":838,"passed_time":0.6060853945,"remaining_time":0.1163048254},
{"learn":[2.944431841],"iteration":839,"passed_time":0.6064624834,"remaining_time":0.1155166635},
{"learn":[2.94203058],"iteration":840,"passed_time":0.6068686977,"remaining_time":0.1147349857},
{"learn":[2.94145425],"iteration":841,"passed_time":0.6073367463,"remaining_time":0.1139658027},
{"learn":[2.940554819],"iteration":842,"passed_time":0.6077876696,"remaining_time":0.1131941449},
{"learn":[2.939414606],"iteration":843,"passed_time":0.6081865505,"remaining_time":0.1124136278},
{"learn":[2.937107853],"iteration":844,"passed_time":0.6085620143,"remaining_time":0.1116297186},
{"learn":[2.936085166],"iteration":845,"passed_time":0.6088830191,"remaining_time":0.1108368616},
{"learn":[2.933439197],"iteration":846,"passed_time":0.6092486911,"remaining_time":0.1100531874},
{"learn":[2.930151225],"iteration":847,"passed_time":0.6095661958,"remaining_time":0.1092618653},
{"learn":[2.928166886],"iteration":848,"passed_time":0.6098788671,"remaining_time":0.1084707997},
{"learn":[2.924320997],"iteration":849,"passed_time":0.6102702479,"remaining_time":0.1076947496},
{"learn":[2.921174658],"iteration":850,"passed_time":0.6106464617,"remaining_time":0.1069169481},
{"learn":[2.919617908],"iteration":851,"passed_time":0.6110464676,"remaining_time":0.1061442221},
{"learn":[2.918800049],"iteration":852,"passed_time":0.6115073911,"remaining_time":0.1053828681},
{"learn":[2.916931994],"iteration":853,"passed_time":0.6119136887,"remaining_time":0.1046128789},
{"learn":[2.915079695],"iteration":854,"passed_time":0.612268444,"remaining_time":0.1038349993},
{"learn":[2.913723898],"iteration":855,"passed_time":0.6126058656,"remaining_time":0.1030551923},
{"learn":[2.913423978],"iteration":856,"passed_time":0.6130469971,"remaining_time":0.102293723},
{"learn":[2.910824972],"iteration":857,"passed_time":0.6133967523,"remaining_time":0.1015178774},
{"learn":[2.908397582],"iteration":858,"passed_time":0.6137209654,"remaining_time":0.1007388313},
{"learn":[2.908221016],"iteration":859,"passed_time":0.6141088044,"remaining_time":0.09997120072},
{"learn":[2.908151399],"iteration":860,"passed_time":0.6145165605,"remaining_time":0.09920766772},
{"learn":[2.907017896],"iteration":861,"passed_time":0.6148958994,"remaining_time":0.09844041081},
{"learn":[2.906289411],"iteration":862,"passed_time":0.6153020304,"remaining_time":0.0976783061},
{"learn":[2.905445827],"iteration":863,"passed_time":0.6157140781,"remaining_time":0.09691795674},
{"learn":[2.904612492],"iteration":864,"passed_time":0.6161087506,"remaining_time":0.09615570096},
{"learn":[2.902710032],"iteration":865,"passed_time":0.6165175483,"remaining_time":0.09539647976},
{"learn":[2.901981927],"iteration":866,"passed_time":0.6169438046,"remaining_time":0.09464074511},
{"learn":[2.901148351],"iteration":867,"passed_time":0.6173847277,"remaining_time":0.09388800007},
{"learn":[2.899868474],"iteration":868,"passed_time":0.6177921921,"remaining_time":0.09313092884},
{"learn":[2.898342425],"iteration":869,"passed_time":0.6181665726,"remaining_time":0.09236971775},
{"learn":[2.897512868],"iteration":870,"passed_time":0.6185197445,"remaining_time":0.09160625378},
{"learn":[2.895921381],"iteration":871,"passed_time":0.6189129169,"remaining_time":0.09084960249},
{"learn":[2.893730636],"iteration":872,"passed_time":0.6193068394,"remaining_time":0.09009389302},
{"learn":[2.893582084],"iteration":873,"passed_time":0.6197064286,"remaining_time":0.08933982839},
{"learn":[2.891887633],"iteration":874,"passed_time":0.6201603103,"remaining_time":0.08859433005},
{"learn":[2.889616318],"iteration":875,"passed_time":0.6206936932,"remaining_time":0.08786075109},
{"learn":[2.886475106],"iteration":876,"passed_time":0.6211187828,"remaining_time":0.08711244046},
{"learn":[2.885033426],"iteration":877,"passed_time":0.6216109151,"remaining_time":0.08637418182},
{"learn":[2.881939117],"iteration":878,"passed_time":0.6221567981,"remaining_time":0.08564388233},
{"learn":[2.881116745],"iteration":879,"passed_time":0.6225231368,"remaining_time":0.08488951866},
{"learn":[2.878437823],"iteration":880,"passed_time":0.6229063092,"remaining_time":0.08413830964},
{"learn":[2.875622933],"iteration":881,"passed_time":0.6232866064,"remaining_time":0.08338755052},
{"learn":[2.874670287],"iteration":882,"passed_time":0.6236645287,"remaining_time":0.0826373158},
{"learn":[2.874079278],"iteration":883,"passed_time":0.6241036601,"remaining_time":0.0818959554},
{"learn":[2.873928514],"iteration":884,"passed_time":0.6244822907,"remaining_time":0.08114741631},
{"learn":[2.87240764],"iteration":885,"passed_time":0.624840671,"remaining_time":0.08039710665},
{"learn":[2.87130895],"iteration":886,"passed_time":0.6251730509,"remaining_time":0.07964436838},
{"learn":[2.870512789],"iteration":887,"passed_time":0.6255357646,"remaining_time":0.07889640274},
{"learn":[2.869110034],"iteration":888,"passed_time":0.6258815614,"remaining_time":0.07814719158},
{"learn":[2.868395364],"iteration":889,"passed_time":0.6262078995,"remaining_time":0.07739648196},
{"learn":[2.86735678],"iteration":890,"passed_time":0.6265773216,"remaining_time":0.07665199557},
{"learn":[2.865714959],"iteration":891,"passed_time":0.627057037,"remaining_time":0.07592170403},
{"learn":[2.863681839],"iteration":892,"passed_time":0.6273916253,"remaining_time":0.07517458444},
{"learn":[2.862344594],"iteration":893,"passed_time":0.6278487154,"remaining_time":0.07444291256},
{"learn":[2.860954443],"iteration":894,"passed_time":0.6282760967,"remaining_time":0.07370836888},
{"learn":[2.859581681],"iteration":895,"passed_time":0.6286753109,"remaining_time":0.07297124144},
{"learn":[2.858694062],"iteration":896,"passed_time":0.6290134409,"remaining_time":0.0722278533},
{"learn":[2.857348163],"iteration":897,"passed_time":0.6293566543,"remaining_time":0.07148594514},
{"learn":[2.854505978],"iteration":898,"passed_time":0.6297635769,"remaining_time":0.0707520815},
{"learn":[2.853034573],"iteration":899,"passed_time":0.6301161655,"remaining_time":0.07001290727},
{"learn":[2.852323311],"iteration":900,"passed_time":0.6304383785,"remaining_time":0.06927125358},
{"learn":[2.850451325],"iteration":901,"passed_time":0.6308042173,"remaining_time":0.06853526973},
{"learn":[2.850393177],"iteration":902,"passed_time":0.6309980535,"remaining_time":0.06778162922},
{"learn":[2.849521225],"iteration":903,"passed_time":0.6313523087,"remaining_time":0.06704626287},
{"learn":[2.848075132],"iteration":904,"passed_time":0.6317096056,"remaining_time":0.06631205805},
{"learn":[2.847124718],"iteration":905,"passed_time":0.6320076933,"remaining_time":0.06557254214},
{"learn":[2.844133905],"iteration":906,"passed_time":0.6323681987,"remaining_time":0.06484039964},
{"learn":[2.843176119],"iteration":907,"passed_time":0.6327451209,"remaining_time":0.06411073912},
{"learn":[2.840033154],"iteration":908,"passed_time":0.6330975011,"remaining_time":0.0633793978},
{"learn":[2.837059821],"iteration":909,"passed_time":0.6334302143,"remaining_time":0.06264694427},
{"learn":[2.835358943],"iteration":910,"passed_time":0.6337740111,"remaining_time":0.06191645114},
{"learn":[2.83305968],"iteration":911,"passed_time":0.6341113077,"remaining_time":0.06118617881},
{"learn":[2.829653997],"iteration":912,"passed_time":0.6345478558,"remaining_time":0.06046622503},
{"learn":[2.82827261],"iteration":913,"passed_time":0.6348699439,"remaining_time":0.05973612163},
{"learn":[2.827361036],"iteration":914,"passed_time":0.6351679899,"remaining_time":0.05900467666},
{"learn":[2.827038824],"iteration":915,"passed_time":0.6355658291,"remaining_time":0.05828332931},
{"learn":[2.824980485],"iteration":916,"passed_time":0.6359315012,"remaining_time":0.05755977601},
{"learn":[2.822957217],"iteration":917,"passed_time":0.6363087984,"remaining_time":0.05683804082},
{"learn":[2.821607201],"iteration":918,"passed_time":0.6371649777,"remaining_time":0.05615926354},
{"learn":[2.819405779],"iteration":919,"passed_time":0.6375276497,"remaining_time":0.05543718693},
{"learn":[2.81645881],"iteration":920,"passed_time":0.6378796549,"remaining_time":0.05471497583},
{"learn":[2.814089639],"iteration":921,"passed_time":0.6383073696,"remaining_time":0.0539999727},
{"learn":[2.812220771],"iteration":922,"passed_time":0.6386248742,"remaining_time":0.05327639796},
{"learn":[2.812076378],"iteration":923,"passed_time":0.6389440873,"remaining_time":0.05255384268},
{"learn":[2.810463536],"iteration":924,"passed_time":0.6392318832,"remaining_time":0.05182961215},
{"learn":[2.808706732],"iteration":925,"passed_time":0.6395455545,"remaining_time":0.05110839204},
{"learn":[2.808450939],"iteration":926,"passed_time":0.6398692676,"remaining_time":0.050388842},
{"learn":[2.806566183],"iteration":927,"passed_time":0.6401624803,"remaining_time":0.04966777864},
{"learn":[2.804562414],"iteration":928,"passed_time":0.6405194022,"remaining_time":0.04895250544},
{"learn":[2.802982691],"iteration":929,"passed_time":0.6408869909,"remaining_time":0.04823880577},
{"learn":[2.802835092],"iteration":930,"passed_time":0.6411946205,"remaining_time":0.04752140581},
{"learn":[2.802064959],"iteration":931,"passed_time":0.6414959166,"remaining_time":0.0468044231},
{"learn":[2.800156003],"iteration":932,"passed_time":0.6418910891,"remaining_time":0.04609507285},
{"learn":[2.797516136],"iteration":933,"passed_time":0.6422382609,"remaining_time":0.04538300344},
{"learn":[2.796150528],"iteration":934,"passed_time":0.6426238915,"remaining_time":0.04467438818},
{"learn":[2.796082075],"iteration":935,"passed_time":0.6429681049,"remaining_time":0.04396363111},
{"learn":[2.795358549],"iteration":936,"passed_time":0.6433001932,"remaining_time":0.04325284116},
{"learn":[2.793904687],"iteration":937,"passed_time":0.6436535734,"remaining_time":0.04254426604},
{"learn":[2.792708993],"iteration":938,"passed_time":0.6440164121,"remaining_time":0.04183706191},
{"learn":[2.792221748],"iteration":939,"passed_time":0.6444203764,"remaining_time":0.04113321551},
{"learn":[2.790317438],"iteration":940,"passed_time":0.6447607147,"remaining_time":0.04042601718},
{"learn":[2.78917382],"iteration":941,"passed_time":0.6451372619,"remaining_time":0.03972182717},
{"learn":[2.788485972],"iteration":942,"passed_time":0.6455359345,"remaining_time":0.03901966942},
{"learn":[2.787726758],"iteration":943,"passed_time":0.6459396488,"remaining_time":0.03831845374},
{"learn":[2.787694266],"iteration":944,"passed_time":0.6462351115,"remaining_time":0.03761156733},
{"learn":[2.785252421],"iteration":945,"passed_time":0.6465704914,"remaining_time":0.03690782932},
{"learn":[2.784105501],"iteration":946,"passed_time":0.6469543721,"remaining_time":0.03620758365},
{"learn":[2.783428227],"iteration":947,"passed_time":0.647379545,"remaining_time":0.0355102704},
{"learn":[2.782901044],"iteration":948,"passed_time":0.6477684674,"remaining_time":0.03481158255},
{"learn":[2.780080979],"iteration":949,"passed_time":0.6481622649,"remaining_time":0.03411380341},
{"learn":[2.778245063],"iteration":950,"passed_time":0.6485162284,"remaining_time":0.03341461114},
{"learn":[2.776885739],"iteration":951,"passed_time":0.6488644836,"remaining_time":0.03271585631},
{"learn":[2.775453338],"iteration":952,"passed_time":0.6492109053,"remaining_time":0.03201774664},
{"learn":[2.774469385],"iteration":953,"passed_time":0.6496142863,"remaining_time":0.03132312072},
{"learn":[2.773546577],"iteration":954,"passed_time":0.6499334576,"remaining_time":0.03062513675},
{"learn":[2.773164876],"iteration":955,"passed_time":0.6502648375,"remaining_time":0.02992850717},
{"learn":[2.771041738],"iteration":956,"passed_time":0.650792637,"remaining_time":0.02924146645},
{"learn":[2.76830721],"iteration":957,"passed_time":0.6511654341,"remaining_time":0.02854796267},
{"learn":[2.766465455],"iteration":958,"passed_time":0.6514766887,"remaining_time":0.0278524966},
{"learn":[2.766335743],"iteration":959,"passed_time":0.6519119452,"remaining_time":0.02716299771},
{"learn":[2.764981221],"iteration":960,"passed_time":0.6522679504,"remaining_time":0.02647081172},
{"learn":[2.761844013],"iteration":961,"passed_time":0.652625164,"remaining_time":0.02577937238},
{"learn":[2.760385149],"iteration":962,"passed_time":0.6530686705,"remaining_time":0.02509194269},
{"learn":[2.75872565],"iteration":963,"passed_time":0.6534510095,"remaining_time":0.02440273479},
{"learn":[2.75748647],"iteration":964,"passed_time":0.6538579322,"remaining_time":0.02371505453},
{"learn":[2.756099648],"iteration":965,"passed_time":0.6542143541,"remaining_time":0.02302617809},
{"learn":[2.755664402],"iteration":966,"passed_time":0.6545361088,"remaining_time":0.0223368062},
{"learn":[2.754476299],"iteration":967,"passed_time":0.6550156159,"remaining_time":0.02165340879},
{"learn":[2.753718329],"iteration":968,"passed_time":0.6553548292,"remaining_time":0.02096594397},
{"learn":[2.75208192],"iteration":969,"passed_time":0.6557575435,"remaining_time":0.02028116114},
{"learn":[2.750749307],"iteration":970,"passed_time":0.6561785497,"remaining_time":0.0195975056},
{"learn":[2.749917989],"iteration":971,"passed_time":0.6565765139,"remaining_time":0.01891372674},
{"learn":[2.749848319],"iteration":972,"passed_time":0.6569709364,"remaining_time":0.01823043708},
{"learn":[2.747803251],"iteration":973,"passed_time":0.6573933593,"remaining_time":0.01754848803},
{"learn":[2.746766535],"iteration":974,"passed_time":0.65777974,"remaining_time":0.01686614718},
{"learn":[2.74580965],"iteration":975,"passed_time":0.6582007462,"remaining_time":0.01618526425},
{"learn":[2.742769345],"iteration":976,"passed_time":0.6585979187,"remaining_time":0.01550435223},
{"learn":[2.740953244],"iteration":977,"passed_time":0.6589742159,"remaining_time":0.01482355087},
{"learn":[2.738555751],"iteration":978,"passed_time":0.6594462646,"remaining_time":0.01414542549},
{"learn":[2.737036659],"iteration":979,"passed_time":0.6598655208,"remaining_time":0.01346664328},
{"learn":[2.736764573],"iteration":980,"passed_time":0.6602282761,"remaining_time":0.01278729587},
{"learn":[2.735662475],"iteration":981,"passed_time":0.6606400738,"remaining_time":0.01210949219},
{"learn":[2.734223622],"iteration":982,"passed_time":0.6609832039,"remaining_time":0.01143104218},
{"learn":[2.731653213],"iteration":983,"passed_time":0.6613818764,"remaining_time":0.01075417685},
{"learn":[2.73079479],"iteration":984,"passed_time":0.6617861324,"remaining_time":0.01007796141},
{"learn":[2.729938321],"iteration":985,"passed_time":0.6622524309,"remaining_time":0.009403178533},
{"learn":[2.729187565],"iteration":986,"passed_time":0.662621228,"remaining_time":0.008727533905},
{"learn":[2.727058514],"iteration":987,"passed_time":0.6629636081,"remaining_time":0.008052189572},
{"learn":[2.725350657],"iteration":988,"passed_time":0.6633236134,"remaining_time":0.007377714608},
{"learn":[2.724364145],"iteration":989,"passed_time":0.6637587032,"remaining_time":0.006704633365},
{"learn":[2.722520898],"iteration":990,"passed_time":0.6642187099,"remaining_time":0.006032258718},
{"learn":[2.722093468],"iteration":991,"passed_time":0.664627466,"remaining_time":0.005359898919},
{"learn":[2.720087606],"iteration":992,"passed_time":0.6649771795,"remaining_time":0.004687653833},
{"learn":[2.719262618],"iteration":993,"passed_time":0.6654390613,"remaining_time":0.004016734776},
{"learn":[2.718510959],"iteration":994,"passed_time":0.6657874831,"remaining_time":0.003345665744},
{"learn":[2.718295466],"iteration":995,"passed_time":0.6661595719,"remaining_time":0.002675339646},
{"learn":[2.716477826],"iteration":996,"passed_time":0.6665392858,"remaining_time":0.002005634762},
{"learn":[2.716069267],"iteration":997,"passed_time":0.6669757506,"remaining_time":0.001336624751},
{"learn":[2.715237354],"iteration":998,"passed_time":0.6673322975,"remaining_time":0.0006680002978},
{"learn":[2.713266586],"iteration":999,"passed_time":0.6676913445,"remaining_time":0}
]}